Workbook
Name Staff: 'Raw data'!$A$2:$N$742

Sheet Raw data
A1: Names | B1: Building | C1: Department | D1: Status | E1: Hiring date | F1: Benefits | G1: Salary | H1: Rating
A2: Abbott, James | B2: North | C2: Quality Assurance | D2: Full Time | E2: 36526 | F2: DMR | G2: 29260 | H2: 4
A3: Acosta, Robert | B3: Main | C3: Quality Assurance | D3: Full Time | E3: 39137 | F3: DMR | G3: 39000 | H3: 5
A4: Adams, David | B4: Main | C4: Product Development | D4: Full Time | E4: 40198 | F4: D | G4: 49260 | H4: 3
A5: Adkins, Michael | B5: North | C5: Quality Assurance | D5: Full Time | E5: 40574 | F5: R | G5: 24840 | H5: 1
A6: Aguilar, Kevin | B6: West | C6: Quality Assurance | D6: Full Time | E6: 36290 | F6: R | G6: 39000 | H6: 3
A7: Alexander, Charles | B7: West | C7: Manufacturing Admin | D7: Contract | E7: 36765 | G7: 74500 | H7: 4
A8: Allen, Thomas | B8: Main | C8: Manufacturing | D8: Full Time | E8: 38807 | F8: DMR | G8: 79730 | H8: 2
A9: Allison, Timothy | B9: Main | C9: Creative | D9: Full Time | E9: 40918 | F9: M | G9: 82500 | H9: 5
A10: Alvarado, Sonia | B10: Main | C10: IT | D10: Half-Time | E10: 40807 | F10: DM | G10: 35045 | H10: 4
A11: Alvarez, Steven | B11: Taft | C11: Quality Assurance | D11: Contract | E11: 40587 | G11: 89450 | H11: 2
A12: Anderson, Teason | B12: Watson | C12: Account Management | D12: Contract | E12: 36375 | G12: 71300 | H12: 5
A13: Andrews, Diane | B13: North | C13: Account Management | D13: Hourly | E13: 36028 | G13: 16688 | H13: 3
A14: Anthony, Robert | B14: Watson | C14: IT | D14: Half-Time | E14: 40393 | F14: DMR | G14: 16925 | H14: 1
A15: Armstrong, David | B15: North | C15: Quality Control | D15: Contract | E15: 35826 | G15: 45030 | H15: 3
A16: Arnold, Cole | B16: North | C16: Sales | D16: Full Time | E16: 40235 | F16: R | G16: 22860 | H16: 5
A17: Ashley, Michael | B17: North | C17: Account Management | D17: Full Time | E17: 40477 | F17: M | G17: 63206 | H17: 1
A18: Atkins, Kevin | B18: North | C18: Manufacturing | D18: Hourly | E18: 35982 | G18: 8904 | H18: 3
A19: Atkinson, Danielle | B19: North | C19: Account Management | D19: Full Time | E19: 37701 | F19: DM | G19: 23560 | H19: 3
A20: Austin, William | B20: Main | C20: Account Management | D20: Full Time | E20: 39335 | F20: DMR | G20: 62688 | H20: 2
A21: Avila, Jody | B21: Main | C21: Quality Assurance | D21: Hourly | E21: 40515 | G21: 33508 | H21: 4
A22: Ayala, Polly | B22: Main | C22: Account Management | D22: Full Time | E22: 39174 | F22: DMR | G22: 23320 | H22: 4
A23: Ayers, Douglas | B23: Main | C23: Manufacturing | D23: Contract | E23: 40462 | G23: 52940 | H23: 4
A24: Bailey, Victor | B24: Watson | C24: Research Center | D24: Full Time | E24: 37684 | F24: R | G24: 42800 | H24: 5
A25: Baker, Barney | B25: Taft | C25: Creative | D25: Contract | E25: 40550 | G25: 80050 | H25: 2
A26: Baldwin, Ray | B26: Watson | C26: Quality Assurance | D26: Full Time | E26: 36514 | F26: R | G26: 48250 | H26: 3
A27: Ball, Kirk | B27: North | C27: Sales | D27: Full Time | E27: 41209 | F27: DM | G27: 87980 | H27: 1
A28: Ballard, Martin | B28: South | C28: IT | D28: Full Time | E28: 39085 | F28: DMR | G28: 87030 | H28: 3
A29: Banks, Ryan | B29: Main | C29: IT | D29: Hourly | E29: 37711 | G29: 21648 | H29: 2
A30: Barber, Robbie | B30: North | C30: Manufacturing | D30: Full Time | E30: 36332 | F30: M | G30: 37760 | H30: 2
A31: Barker, Heidi | B31: West | C31: Account Management | D31: Full Time | E31: 40264 | F31: D | G31: 29760 | H31: 2
A32: Barnes, Grant | B32: Main | C32: Quality Assurance | D32: Hourly | E32: 35861 | G32: 12836 | H32: 5
A33: Barnett, Brenda | B33: North | C33: Human Resources | D33: Full Time | E33: 39683 | F33: DMR | G33: 47350 | H33: 5
A34: Barr, Jennifer | B34: North | C34: Marketing | D34: Full Time | E34: 36116 | F34: D | G34: 49770 | H34: 1
A35: Barrett, John | B35: North | C35: Quality Control | D35: Full Time | E35: 36549 | F35: R | G35: 35460 | H35: 1
A36: Barron, Michael | B36: West | C36: Manufacturing | D36: Full Time | E36: 39655 | F36: D | G36: 34480 | H36: 3
A37: Bartlett, Julia | B37: Watson | C37: Professional Training Group | D37: Full Time | E37: 40818 | F37: M | G37: 44560 | H37: 2
A38: Barton, Barry | B38: North | C38: Professional Training Group | D38: Full Time | E38: 40551 | F38: DMR | G38: 71730 | H38: 1
A39: Bass, Justin | B39: North | C39: Product Development | D39: Contract | E39: 37641 | G39: 31970 | H39: 5
A40: Bates, Verna | B40: North | C40: Manufacturing | D40: Full Time | E40: 37068 | F40: DM | G40: 66010 | H40: 5
A41: Bauer, Chris | B41: West | C41: IT | D41: Half-Time | E41: 37470 | F41: DMR | G41: 33810 | H41: 5
A42: Baxter, Teresa | B42: Taft | C42: Manufacturing | D42: Half-Time | E42: 35807 | F42: DMR | G42: 48835 | H42: 5
A43: Bean, Deborah | B43: Main | C43: Account Management | D43: Full Time | E43: 40332 | F43: DMR | G43: 47340 | H43: 2
A44: Beard, Sandi | B44: Watson | C44: Quality Control | D44: Half-Time | E44: 40410 | F44: R | G44: 38105 | H44: 2
A45: Beasley, Timothy | B45: North | C45: Quality Control | D45: Full Time | E45: 36672 | F45: DM | G45: 65320 | H45: 5
A46: Beck, Craig | B46: North | C46: Environmental Compliance | D46: Full Time | E46: 41018 | F46: DMR | G46: 46220 | H46: 3
A47: Becker, Gretchen | B47: West | C47: Facilities/Engineering | D47: Full Time | E47: 37960 | F47: DMR | G47: 66890 | H47: 5
A48: Bell, David | B48: South | C48: Manufacturing | D48: Contract | E48: 39378 | G48: 35460 | H48: 3
A49: Bennett, Chris | B49: Taft | C49: IT | D49: Full Time | E49: 40370 | F49: DMR | G49: 66840 | H49: 4
A50: Benson, Troy | B50: Watson | C50: Manufacturing | D50: Contract | E50: 40473 | G50: 28260 | H50: 5
A51: Berry, Jacklyn | B51: Taft | C51: Manufacturing | D51: Contract | E51: 39144 | G51: 64430 | H51: 4
A52: Best, Lara | B52: Main | C52: IT | D52: Full Time | E52: 38227 | F52: R | G52: 86200 | H52: 3
A53: Bishop, Juan | B53: North | C53: Marketing | D53: Half-Time | E53: 39457 | F53: DMR | G53: 31255 | H53: 5
A54: Black, Cliff | B54: Watson | C54: Quality Assurance | D54: Full Time | E54: 37625 | F54: R | G54: 82490 | H54: 5
A55: Blackburn, Kathryn | B55: West | C55: Manufacturing | D55: Contract | E55: 39538 | G55: 62780 | H55: 4
A56: Blackwell, Brandon | B56: West | C56: Quality Control | D56: Contract | E56: 36193 | G56: 58250 | H56: 2
A57: Blair, Sperry | B57: West | C57: Environmental Compliance | D57: Full Time | E57: 40106 | F57: DM | G57: 51180 | H57: 3
A58: Blake, Thomas | B58: South | C58: Quality Control | D58: Contract | E58: 39272 | G58: 35240 | H58: 3
A59: Blankenship, Roger | B59: North | C59: Quality Assurance | D59: Full Time | E59: 38784 | F59: DMR | G59: 78710 | H59: 4
A60: Blevins, Carey | B60: Taft | C60: Marketing | D60: Full Time | E60: 40395 | F60: DMR | G60: 57560 | H60: 4
A61: Bond, John | B61: North | C61: Environmental Compliance | D61: Half-Time | E61: 39417 | F61: M | G61: 46095 | H61: 3
A62: Booker, Judith | B62: West | C62: Facilities/Engineering | D62: Contract | E62: 39040 | G62: 62150 | H62: 4
A63: Boone, Eric | B63: Taft | C63: Major Mfg Projects | D63: Contract | E63: 40263 | F63: M | G63: 71190 | H63: 4
A64: Booth, Raquel | B64: West | C64: Account Management | D64: Hourly | E64: 35946 | G64: 14332 | H64: 5
A65: Bowen, Kes | B65: West | C65: Quality Control | D65: Contract | E65: 41094 | G65: 59128 | H65: 4
A66: Bowers, Tammy | B66: South | C66: Sales | D66: Half-Time | E66: 40263 | F66: DMR | G66: 49405 | H66: 4
A67: Bowman, Michael | B67: West | C67: Account Management | D67: Contract | E67: 36086 | G67: 47520 | H67: 1
A68: Boyd, Debra | B68: North | C68: Manufacturing | D68: Half-Time | E68: 36604 | F68: R | G68: 46710 | H68: 3
A69: Boyer, John | B69: West | C69: Manufacturing | D69: Full Time | E69: 38798 | F69: R | G69: 73144 | H69: 5
A70: Bradford, Raymond | B70: North | C70: Manufacturing | D70: Contract | E70: 35972 | G70: 71710 | H70: 5
A71: Bradley, David | B71: Main | C71: Manufacturing | D71: Full Time | E71: 39696 | F71: DMR | G71: 69320 | H71: 3
A72: Bradshaw, Sheryl | B72: North | C72: Research/Development | D72: Contract | E72: 39639 | G72: 64720 | H72: 5
A73: Brady, Traci | B73: Main | C73: Manufacturing | D73: Full Time | E73: 40634 | F73: DMR | G73: 47440 | H73: 3
A74: Branch, Brady | B74: North | C74: Quality Assurance | D74: Contract | E74: 39720 | G74: 43320 | H74: 5
A75: Brewer, Khurrum | B75: Main | C75: Training | D75: Half-Time | E75: 40779 | F75: DM | G75: 30445 | H75: 1
A76: Bridges, Jeff | B76: West | C76: Manufacturing | D76: Full Time | E76: 40578 | F76: DMR | G76: 43820 | H76: 2
A77: Briggs, Bryan | B77: Main | C77: Facilities/Engineering | D77: Contract | E77: 35848 | G77: 85480 | H77: 5
A78: Brock, Ensley | B78: Taft | C78: Manufacturing | D78: Full Time | E78: 40424 | F78: M | G78: 39520 | H78: 5
A79: Brooks, Richard | B79: West | C79: Marketing | D79: Half-Time | E79: 39098 | F79: R | G79: 47705 | H79: 5
A80: Brown, Donald | B80: North | C80: Quality Control | D80: Hourly | E80: 40360 | G80: 33752 | H80: 3
A81: Browning, Kathleen | B81: South | C81: Manufacturing | D81: Contract | E81: 36704 | G81: 57760 | H81: 3
A82: Bruce, Kevin | B82: Main | C82: Quality Assurance | D82: Hourly | E82: 39293 | G82: 26484 | H82: 5
A83: Bryan, Thomas | B83: South | C83: Sales | D83: Full Time | E83: 40533 | F83: D | G83: 62180 | H83: 2
A84: Bryant, Douglas | B84: North | C84: Marketing | D84: Full Time | E84: 36463 | F84: DMR | G84: 44220 | H84: 3
A85: Buchanan, Dennis | B85: North | C85: Quality Control | D85: Contract | E85: 39648 | G85: 45105 | H85: 1
A86: Buckel, Patricia | B86: Taft | C86: Marketing | D86: Full Time | E86: 41070 | F86: DM | G86: 73930 | H86: 1
A87: Bullock, Greg | B87: North | C87: Facilities/Engineering | D87: Hourly | E87: 40925 | G87: 14568 | H87: 3
A88: Burgess, Cherie | B88: North | C88: Manufacturing | D88: Full Time | E88: 35932 | F88: R | G88: 89740 | H88: 5
A89: Burke, Michael | B89: Taft | C89: Sales | D89: Contract | E89: 39011 | G89: 86470 | H89: 4
A90: Burnett, Kevin | B90: Main | C90: Account Management | D90: Full Time | E90: 40624 | F90: D | G90: 86500 | H90: 1
A91: Burns, Fiona | B91: Main | C91: Manufacturing | D91: Hourly | E91: 40574 | G91: 28424 | H91: 4
A92: Burton, Cam | B92: West | C92: Training | D92: Full Time | E92: 39704 | F92: D | G92: 58290 | H92: 5
A93: Bush, Rena | B93: South | C93: Marketing | D93: Contract | E93: 39330 | G93: 81930 | H93: 5
A94: Butler, Roy | B94: Taft | C94: Manufacturing | D94: Full Time | E94: 36198 | F94: D | G94: 81400 | H94: 2
A95: Byrd, Asa | B95: Watson | C95: Sales | D95: Hourly | E95: 37827 | G95: 11044 | H95: 2
A96: Cabe, Max | B96: Main | C96: Account Management | D96: Half-Time | E96: 40166 | F96: D | G96: 25245 | H96: 5
A97: Cain, Lon | B97: North | C97: Account Management | D97: Full Time | E97: 39262 | F97: D | G97: 63440 | H97: 3
A98: Caldwell, Pete | B98: Main | C98: Marketing | D98: Full Time | E98: 36456 | F98: R | G98: 43460 | H98: 5
A99: Calhoun, Dac Vinh | B99: North | C99: Product Development | D99: Half-Time | E99: 40184 | F99: D | G99: 21220 | H99: 3
A100: Callahan, Marilyn | B100: South | C100: Manufacturing | D100: Full Time | E100: 39181 | F100: R | G100: 23330 | H100: 4
...

Sheet Staff table
A1: Names | B1: Building | C1: Department | D1: Status | E1: Hiring date | F1: Benefits | G1: Salary | H1: Rating | I1: Bonus | J1: Taxes | K1: After tax salary | L1: Salary with bonus | S1: Tax | T1: After tax salary | V1: Fixed amt | W1: Tax rate | Y1: Difference | Z1: Actual Tax | AA1: Salary After tax
A2: Tate, Zachary | B2: Taft | C2: Manufacturing | D2: Full Time | E2: 35801 | F2: DMR | G2: 78570 | H2: 1 | I2: =IF(OR(Table2[[#This Row],[Rating]]=4,Table2[[#This Row],[Rating]]=5), 0.05*Table2[[#This Row],[Salary]],0) -> 0 | J2: =VLOOKUP(Table2[[#This Row],[Salary]],'Tax rates'!A$2:C$8, 2) + VLOOKUP(Table2[[#This Row],[Salary]],'Tax rates'!A$2:C$8, 3) * (Table2[[#This Row],[Salary]] - VLOOKUP(Table2[[#This Row],[Salary]],'Tax rates'!A$2:C$8,1)) -> 13224.9 | K2: =Table2[[#This Row],[Salary]]-Table2[[#This Row],[Taxes]] -> 65345.1 | L2: =Table2[[#This Row],[After tax salary]]+Table2[[#This Row],[Bonus]] -> 65345.1 | O2: =VLOOKUP(Table2[[#This Row],[Salary]],'Tax rates'!A1:D8,2) -> 4453.5 | P2: =VLOOKUP(Table2[[#This Row],[Salary]],'Tax rates'!A1:D8,3) -> 0.22 | Q2: =VLOOKUP(Table2[[#This Row],[Salary]],'Tax rates'!A1:D8,1) -> 38700 | R2: =Table2[[#This Row],[Salary]]-Q2 -> 39870 | S2: =O2+P2*R2 -> 13224.9 | T2: =Table2[[#This Row],[Salary]]-S2 -> 65345.1 | V2: =VLOOKUP(Table2[[#This Row],[Salary]],'Tax rates'!A1:D8,2) -> 4453.5 | W2: =VLOOKUP(Table2[[#This Row],[Salary]],'Tax rates'!A1:D8,3) -> 0.22 | X2: =VLOOKUP(Table2[[#This Row],[Salary]],'Tax rates'!A1:D8,1) -> 38700 | Y2: =Table2[[#This Row],[Salary]]-X2 -> 39870 | Z2: =V2+W2*Y2 -> 13224.9 | AA2: =Table2[[#This Row],[Salary]]-Z2 -> 65345.1
A3: Wilcox, Robert | B3: Main | C3: Quality Assurance | D3: Contract | E3: 35806 | G3: 86100 | H3: 4 | I3: =IF(OR(Table2[[#This Row],[Rating]]=4,Table2[[#This Row],[Rating]]=5), 0.05*Table2[[#This Row],[Salary]],0) -> 4305 | J3: =VLOOKUP(Table2[[#This Row],[Salary]],'Tax rates'!A$2:C$8, 2) + VLOOKUP(Table2[[#This Row],[Salary]],'Tax rates'!A$2:C$8, 3) * (Table2[[#This Row],[Salary]] - VLOOKUP(Table2[[#This Row],[Salary]],'Tax rates'!A$2:C$8,1)) -> 14953.5 | K3: =Table2[[#This Row],[Salary]]-Table2[[#This Row],[Taxes]] -> 71146.5 | L3: =Table2[[#This Row],[After tax salary]]+Table2[[#This Row],[Bonus]] -> 75451.5
A4: Baxter, Teresa | B4: Taft | C4: Manufacturing | D4: Half-Time | E4: 35807 | F4: DMR | G4: 48835 | H4: 5 | I4: =IF(OR(Table2[[#This Row],[Rating]]=4,Table2[[#This Row],[Rating]]=5), 0.05*Table2[[#This Row],[Salary]],0) -> 2441.75 | J4: =VLOOKUP(Table2[[#This Row],[Salary]],'Tax rates'!A$2:C$8, 2) + VLOOKUP(Table2[[#This Row],[Salary]],'Tax rates'!A$2:C$8, 3) * (Table2[[#This Row],[Salary]] - VLOOKUP(Table2[[#This Row],[Salary]],'Tax rates'!A$2:C$8,1)) -> 6683.2 | K4: =Table2[[#This Row],[Salary]]-Table2[[#This Row],[Taxes]] -> 42151.8 | L4: =Table2[[#This Row],[After tax salary]]+Table2[[#This Row],[Bonus]] -> 44593.55
A5: Farmer, Suzanne | B5: West | C5: Account Management | D5: Full Time | E5: 35821 | F5: M | G5: 22870 | H5: 3 | I5: =IF(OR(Table2[[#This Row],[Rating]]=4,Table2[[#This Row],[Rating]]=5), 0.05*Table2[[#This Row],[Salary]],0) -> 0 | J5: =VLOOKUP(Table2[[#This Row],[Salary]],'Tax rates'!A$2:C$8, 2) + VLOOKUP(Table2[[#This Row],[Salary]],'Tax rates'!A$2:C$8, 3) * (Table2[[#This Row],[Salary]] - VLOOKUP(Table2[[#This Row],[Salary]],'Tax rates'!A$2:C$8,1)) -> 2553.9 | K5: =Table2[[#This Row],[Salary]]-Table2[[#This Row],[Taxes]] -> 20316.1 | L5: =Table2[[#This Row],[After tax salary]]+Table2[[#This Row],[Bonus]] -> 20316.1
A6: Armstrong, David | B6: North | C6: Quality Control | D6: Contract | E6: 35826 | G6: 45030 | H6: 3 | I6: =IF(OR(Table2[[#This Row],[Rating]]=4,Table2[[#This Row],[Rating]]=5), 0.05*Table2[[#This Row],[Salary]],0) -> 0 | J6: =VLOOKUP(Table2[[#This Row],[Salary]],'Tax rates'!A$2:C$8, 2) + VLOOKUP(Table2[[#This Row],[Salary]],'Tax rates'!A$2:C$8, 3) * (Table2[[#This Row],[Salary]] - VLOOKUP(Table2[[#This Row],[Salary]],'Tax rates'!A$2:C$8,1)) -> 5846.1 | K6: =Table2[[#This Row],[Salary]]-Table2[[#This Row],[Taxes]] -> 39183.9 | L6: =Table2[[#This Row],[After tax salary]]+Table2[[#This Row],[Bonus]] -> 39183.9
A7: Grant, Leonard | B7: South | C7: Account Management | D7: Half-Time | E7: 35826 | F7: DMR | G7: 31205 | H7: 2 | I7: =IF(OR(Table2[[#This Row],[Rating]]=4,Table2[[#This Row],[Rating]]=5), 0.05*Table2[[#This Row],[Salary]],0) -> 0 | J7: =VLOOKUP(Table2[[#This Row],[Salary]],'Tax rates'!A$2:C$8, 2) + VLOOKUP(Table2[[#This Row],[Salary]],'Tax rates'!A$2:C$8, 3) * (Table2[[#This Row],[Salary]] - VLOOKUP(Table2[[#This Row],[Salary]],'Tax rates'!A$2:C$8,1)) -> 3554.1 | K7: =Table2[[#This Row],[Salary]]-Table2[[#This Row],[Taxes]] -> 27650.9 | L7: =Table2[[#This Row],[After tax salary]]+Table2[[#This Row],[Bonus]] -> 27650.9
A8: Powers, Tia | B8: North | C8: Facilities/Engineering | D8: Full Time | E8: 35829 | F8: DMR | G8: 61030 | H8: 3 | I8: =IF(OR(Table2[[#This Row],[Rating]]=4,Table2[[#This Row],[Rating]]=5), 0.05*Table2[[#This Row],[Salary]],0) -> 0 | J8: =VLOOKUP(Table2[[#This Row],[Salary]],'Tax rates'!A$2:C$8, 2) + VLOOKUP(Table2[[#This Row],[Salary]],'Tax rates'!A$2:C$8, 3) * (Table2[[#This Row],[Salary]] - VLOOKUP(Table2[[#This Row],[Salary]],'Tax rates'!A$2:C$8,1)) -> 9366.1 | K8: =Table2[[#This Row],[Salary]]-Table2[[#This Row],[Taxes]] -> 51663.9 | L8: =Table2[[#This Row],[After tax salary]]+Table2[[#This Row],[Bonus]] -> 51663.9
A9: Meyers, David | B9: West | C9: Manufacturing | D9: Hourly | E9: 35829 | G9: 29176 | H9: 3 | I9: =IF(OR(Table2[[#This Row],[Rating]]=4,Table2[[#This Row],[Rating]]=5), 0.05*Table2[[#This Row],[Salary]],0) -> 0 | J9: =VLOOKUP(Table2[[#This Row],[Salary]],'Tax rates'!A$2:C$8, 2) + VLOOKUP(Table2[[#This Row],[Salary]],'Tax rates'!A$2:C$8, 3) * (Table2[[#This Row],[Salary]] - VLOOKUP(Table2[[#This Row],[Salary]],'Tax rates'!A$2:C$8,1)) -> 3310.62 | K9: =Table2[[#This Row],[Salary]]-Table2[[#This Row],[Taxes]] -> 25865.38 | L9: =Table2[[#This Row],[After tax salary]]+Table2[[#This Row],[Bonus]] -> 25865.38
A10: Walker, Mike | B10: Watson | C10: Manufacturing | D10: Full Time | E10: 35830 | F10: M | G10: 35460 | H10: 5 | I10: =IF(OR(Table2[[#This Row],[Rating]]=4,Table2[[#This Row],[Rating]]=5), 0.05*Table2[[#This Row],[Salary]],0) -> 1773 | J10: =VLOOKUP(Table2[[#This Row],[Salary]],'Tax rates'!A$2:C$8, 2) + VLOOKUP(Table2[[#This Row],[Salary]],'Tax rates'!A$2:C$8, 3) * (Table2[[#This Row],[Salary]] - VLOOKUP(Table2[[#This Row],[Salary]],'Tax rates'!A$2:C$8,1)) -> 4064.7 | K10: =Table2[[#This Row],[Salary]]-Table2[[#This Row],[Taxes]] -> 31395.3 | L10: =Table2[[#This Row],[After tax salary]]+Table2[[#This Row],[Bonus]] -> 33168.3
A11: Navarro, Marc | B11: Main | C11: Facilities/Engineering | D11: Half-Time | E11: 35842 | F11: D | G11: 23380 | H11: 4 | I11: =IF(OR(Table2[[#This Row],[Rating]]=4,Table2[[#This Row],[Rating]]=5), 0.05*Table2[[#This Row],[Salary]],0) -> 1169 | J11: =VLOOKUP(Table2[[#This Row],[Salary]],'Tax rates'!A$2:C$8, 2) + VLOOKUP(Table2[[#This Row],[Salary]],'Tax rates'!A$2:C$8, 3) * (Table2[[#This Row],[Salary]] - VLOOKUP(Table2[[#This Row],[Salary]],'Tax rates'!A$2:C$8,1)) -> 2615.1 | K11: =Table2[[#This Row],[Salary]]-Table2[[#This Row],[Taxes]] -> 20764.9 | L11: =Table2[[#This Row],[After tax salary]]+Table2[[#This Row],[Bonus]] -> 21933.9
A12: Pugh, Lawrence | B12: South | C12: Quality Assurance | D12: Half-Time | E12: 35842 | F12: M | G12: 39530 | H12: 5 | I12: =IF(OR(Table2[[#This Row],[Rating]]=4,Table2[[#This Row],[Rating]]=5), 0.05*Table2[[#This Row],[Salary]],0) -> 1976.5 | J12: =VLOOKUP(Table2[[#This Row],[Salary]],'Tax rates'!A$2:C$8, 2) + VLOOKUP(Table2[[#This Row],[Salary]],'Tax rates'!A$2:C$8, 3) * (Table2[[#This Row],[Salary]] - VLOOKUP(Table2[[#This Row],[Salary]],'Tax rates'!A$2:C$8,1)) -> 4636.1 | K12: =Table2[[#This Row],[Salary]]-Table2[[#This Row],[Taxes]] -> 34893.9 | L12: =Table2[[#This Row],[After tax salary]]+Table2[[#This Row],[Bonus]] -> 36870.4
A13: Briggs, Bryan | B13: Main | C13: Facilities/Engineering | D13: Contract | E13: 35848 | G13: 85480 | H13: 5 | I13: =IF(OR(Table2[[#This Row],[Rating]]=4,Table2[[#This Row],[Rating]]=5), 0.05*Table2[[#This Row],[Salary]],0) -> 4274 | J13: =VLOOKUP(Table2[[#This Row],[Salary]],'Tax rates'!A$2:C$8, 2) + VLOOKUP(Table2[[#This Row],[Salary]],'Tax rates'!A$2:C$8, 3) * (Table2[[#This Row],[Salary]] - VLOOKUP(Table2[[#This Row],[Salary]],'Tax rates'!A$2:C$8,1)) -> 14804.7 | K13: =Table2[[#This Row],[Salary]]-Table2[[#This Row],[Taxes]] -> 70675.3 | L13: =Table2[[#This Row],[After tax salary]]+Table2[[#This Row],[Bonus]] -> 74949.3
A14: Patton, Corey | B14: West | C14: Marketing | D14: Full Time | E14: 35856 | F14: D | G14: 86830 | H14: 3 | I14: =IF(OR(Table2[[#This Row],[Rating]]=4,Table2[[#This Row],[Rating]]=5), 0.05*Table2[[#This Row],[Salary]],0) -> 0 | J14: =VLOOKUP(Table2[[#This Row],[Salary]],'Tax rates'!A$2:C$8, 2) + VLOOKUP(Table2[[#This Row],[Salary]],'Tax rates'!A$2:C$8, 3) * (Table2[[#This Row],[Salary]] - VLOOKUP(Table2[[#This Row],[Salary]],'Tax rates'!A$2:C$8,1)) -> 15128.7 | K14: =Table2[[#This Row],[Salary]]-Table2[[#This Row],[Taxes]] -> 71701.3 | L14: =Table2[[#This Row],[After tax salary]]+Table2[[#This Row],[Bonus]] -> 71701.3
A15: Chavez, Thomas | B15: Main | C15: Marketing | D15: Full Time | E15: 35857 | F15: R | G15: 82110 | H15: 3 | I15: =IF(OR(Table2[[#This Row],[Rating]]=4,Table2[[#This Row],[Rating]]=5), 0.05*Table2[[#This Row],[Salary]],0) -> 0 | J15: =VLOOKUP(Table2[[#This Row],[Salary]],'Tax rates'!A$2:C$8, 2) + VLOOKUP(Table2[[#This Row],[Salary]],'Tax rates'!A$2:C$8, 3) * (Table2[[#This Row],[Salary]] - VLOOKUP(Table2[[#This Row],[Salary]],'Tax rates'!A$2:C$8,1)) -> 14003.7 | K15: =Table2[[#This Row],[Salary]]-Table2[[#This Row],[Taxes]] -> 68106.3 | L15: =Table2[[#This Row],[After tax salary]]+Table2[[#This Row],[Bonus]] -> 68106.3
A16: Barnes, Grant | B16: Main | C16: Quality Assurance | D16: Hourly | E16: 35861 | G16: 12836 | H16: 5 | I16: =IF(OR(Table2[[#This Row],[Rating]]=4,Table2[[#This Row],[Rating]]=5), 0.05*Table2[[#This Row],[Salary]],0) -> 641.8 | J16: =VLOOKUP(Table2[[#This Row],[Salary]],'Tax rates'!A$2:C$8, 2) + VLOOKUP(Table2[[#This Row],[Salary]],'Tax rates'!A$2:C$8, 3) * (Table2[[#This Row],[Salary]] - VLOOKUP(Table2[[#This Row],[Salary]],'Tax rates'!A$2:C$8,1)) -> 1349.82 | K16: =Table2[[#This Row],[Salary]]-Table2[[#This Row],[Taxes]] -> 11486.18 | L16: =Table2[[#This Row],[After tax salary]]+Table2[[#This Row],[Bonus]] -> 12127.98
A17: Turner, Ray | B17: West | C17: Quality Assurance | D17: Hourly | E17: 35869 | G17: 17912 | H17: 5 | I17: =IF(OR(Table2[[#This Row],[Rating]]=4,Table2[[#This Row],[Rating]]=5), 0.05*Table2[[#This Row],[Salary]],0) -> 895.6 | J17: =VLOOKUP(Table2[[#This Row],[Salary]],'Tax rates'!A$2:C$8, 2) + VLOOKUP(Table2[[#This Row],[Salary]],'Tax rates'!A$2:C$8, 3) * (Table2[[#This Row],[Salary]] - VLOOKUP(Table2[[#This Row],[Salary]],'Tax rates'!A$2:C$8,1)) -> 1958.94 | K17: =Table2[[#This Row],[Salary]]-Table2[[#This Row],[Taxes]] -> 15953.06 | L17: =Table2[[#This Row],[After tax salary]]+Table2[[#This Row],[Bonus]] -> 16848.66
A18: Henry, Craig | B18: North | C18: Quality Assurance | D18: Full Time | E18: 35896 | F18: R | G18: 70280 | H18: 3 | I18: =IF(OR(Table2[[#This Row],[Rating]]=4,Table2[[#This Row],[Rating]]=5), 0.05*Table2[[#This Row],[Salary]],0) -> 0 | J18: =VLOOKUP(Table2[[#This Row],[Salary]],'Tax rates'!A$2:C$8, 2) + VLOOKUP(Table2[[#This Row],[Salary]],'Tax rates'!A$2:C$8, 3) * (Table2[[#This Row],[Salary]] - VLOOKUP(Table2[[#This Row],[Salary]],'Tax rates'!A$2:C$8,1)) -> 11401.1 | K18: =Table2[[#This Row],[Salary]]-Table2[[#This Row],[Taxes]] -> 58878.9 | L18: =Table2[[#This Row],[After tax salary]]+Table2[[#This Row],[Bonus]] -> 58878.9
A19: Lawrence, Ronald | B19: Main | C19: Facilities/Engineering | D19: Contract | E19: 35902 | G19: 63340 | H19: 3 | I19: =IF(OR(Table2[[#This Row],[Rating]]=4,Table2[[#This Row],[Rating]]=5), 0.05*Table2[[#This Row],[Salary]],0) -> 0 | J19: =VLOOKUP(Table2[[#This Row],[Salary]],'Tax rates'!A$2:C$8, 2) + VLOOKUP(Table2[[#This Row],[Salary]],'Tax rates'!A$2:C$8, 3) * (Table2[[#This Row],[Salary]] - VLOOKUP(Table2[[#This Row],[Salary]],'Tax rates'!A$2:C$8,1)) -> 9874.3 | K19: =Table2[[#This Row],[Salary]]-Table2[[#This Row],[Taxes]] -> 53465.7 | L19: =Table2[[#This Row],[After tax salary]]+Table2[[#This Row],[Bonus]] -> 53465.7
A20: Garrison, Chris | B20: North | C20: IT | D20: Full Time | E20: 35903 | F20: DMR | G20: 68520 | H20: 5 | I20: =IF(OR(Table2[[#This Row],[Rating]]=4,Table2[[#This Row],[Rating]]=5), 0.05*Table2[[#This Row],[Salary]],0) -> 3426 | J20: =VLOOKUP(Table2[[#This Row],[Salary]],'Tax rates'!A$2:C$8, 2) + VLOOKUP(Table2[[#This Row],[Salary]],'Tax rates'!A$2:C$8, 3) * (Table2[[#This Row],[Salary]] - VLOOKUP(Table2[[#This Row],[Salary]],'Tax rates'!A$2:C$8,1)) -> 11013.9 | K20: =Table2[[#This Row],[Salary]]-Table2[[#This Row],[Taxes]] -> 57506.1 | L20: =Table2[[#This Row],[After tax salary]]+Table2[[#This Row],[Bonus]] -> 60932.1
A21: Jefferson, Elaine | B21: Taft | C21: Account Management | D21: Full Time | E21: 35918 | F21: DM | G21: 73740 | H21: 4 | I21: =IF(OR(Table2[[#This Row],[Rating]]=4,Table2[[#This Row],[Rating]]=5), 0.05*Table2[[#This Row],[Salary]],0) -> 3687 | J21: =VLOOKUP(Table2[[#This Row],[Salary]],'Tax rates'!A$2:C$8, 2) + VLOOKUP(Table2[[#This Row],[Salary]],'Tax rates'!A$2:C$8, 3) * (Table2[[#This Row],[Salary]] - VLOOKUP(Table2[[#This Row],[Salary]],'Tax rates'!A$2:C$8,1)) -> 12162.3 | K21: =Table2[[#This Row],[Salary]]-Table2[[#This Row],[Taxes]] -> 61577.7 | L21: =Table2[[#This Row],[After tax salary]]+Table2[[#This Row],[Bonus]] -> 65264.7
A22: Dudley, James | B22: South | C22: IT | D22: Contract | E22: 35921 | G22: 63330 | H22: 4 | I22: =IF(OR(Table2[[#This Row],[Rating]]=4,Table2[[#This Row],[Rating]]=5), 0.05*Table2[[#This Row],[Salary]],0) -> 3166.5 | J22: =VLOOKUP(Table2[[#This Row],[Salary]],'Tax rates'!A$2:C$8, 2) + VLOOKUP(Table2[[#This Row],[Salary]],'Tax rates'!A$2:C$8, 3) * (Table2[[#This Row],[Salary]] - VLOOKUP(Table2[[#This Row],[Salary]],'Tax rates'!A$2:C$8,1)) -> 9872.1 | K22: =Table2[[#This Row],[Salary]]-Table2[[#This Row],[Taxes]] -> 53457.9 | L22: =Table2[[#This Row],[After tax salary]]+Table2[[#This Row],[Bonus]] -> 56624.4
A23: Fields, Cathy | B23: Taft | C23: Manufacturing | D23: Contract | E23: 35927 | G23: 76910 | H23: 1 | I23: =IF(OR(Table2[[#This Row],[Rating]]=4,Table2[[#This Row],[Rating]]=5), 0.05*Table2[[#This Row],[Salary]],0) -> 0 | J23: =VLOOKUP(Table2[[#This Row],[Salary]],'Tax rates'!A$2:C$8, 2) + VLOOKUP(Table2[[#This Row],[Salary]],'Tax rates'!A$2:C$8, 3) * (Table2[[#This Row],[Salary]] - VLOOKUP(Table2[[#This Row],[Salary]],'Tax rates'!A$2:C$8,1)) -> 12859.7 | K23: =Table2[[#This Row],[Salary]]-Table2[[#This Row],[Taxes]] -> 64050.3 | L23: =Table2[[#This Row],[After tax salary]]+Table2[[#This Row],[Bonus]] -> 64050.3
A24: Burgess, Cherie | B24: North | C24: Manufacturing | D24: Full Time | E24: 35932 | F24: R | G24: 89740 | H24: 5 | I24: =IF(OR(Table2[[#This Row],[Rating]]=4,Table2[[#This Row],[Rating]]=5), 0.05*Table2[[#This Row],[Salary]],0) -> 4487 | J24: =VLOOKUP(Table2[[#This Row],[Salary]],'Tax rates'!A$2:C$8, 2) + VLOOKUP(Table2[[#This Row],[Salary]],'Tax rates'!A$2:C$8, 3) * (Table2[[#This Row],[Salary]] - VLOOKUP(Table2[[#This Row],[Salary]],'Tax rates'!A$2:C$8,1)) -> 15827.1 | K24: =Table2[[#This Row],[Salary]]-Table2[[#This Row],[Taxes]] -> 73912.9 | L24: =Table2[[#This Row],[After tax salary]]+Table2[[#This Row],[Bonus]] -> 78399.9
A25: Melton, Scott | B25: West | C25: Manufacturing | D25: Full Time | E25: 35938 | F25: M | G25: 55450 | H25: 5 | I25: =IF(OR(Table2[[#This Row],[Rating]]=4,Table2[[#This Row],[Rating]]=5), 0.05*Table2[[#This Row],[Salary]],0) -> 2772.5 | J25: =VLOOKUP(Table2[[#This Row],[Salary]],'Tax rates'!A$2:C$8, 2) + VLOOKUP(Table2[[#This Row],[Salary]],'Tax rates'!A$2:C$8, 3) * (Table2[[#This Row],[Salary]] - VLOOKUP(Table2[[#This Row],[Salary]],'Tax rates'!A$2:C$8,1)) -> 8138.5 | K25: =Table2[[#This Row],[Salary]]-Table2[[#This Row],[Taxes]] -> 47311.5 | L25: =Table2[[#This Row],[After tax salary]]+Table2[[#This Row],[Bonus]] -> 50084
A26: Gallegos, Rick | B26: Main | C26: Product Development | D26: Contract | E26: 35939 | G26: 25120 | H26: 5 | I26: =IF(OR(Table2[[#This Row],[Rating]]=4,Table2[[#This Row],[Rating]]=5), 0.05*Table2[[#This Row],[Salary]],0) -> 1256 | J26: =VLOOKUP(Table2[[#This Row],[Salary]],'Tax rates'!A$2:C$8, 2) + VLOOKUP(Table2[[#This Row],[Salary]],'Tax rates'!A$2:C$8, 3) * (Table2[[#This Row],[Salary]] - VLOOKUP(Table2[[#This Row],[Salary]],'Tax rates'!A$2:C$8,1)) -> 2823.9 | K26: =Table2[[#This Row],[Salary]]-Table2[[#This Row],[Taxes]] -> 22296.1 | L26: =Table2[[#This Row],[After tax salary]]+Table2[[#This Row],[Bonus]] -> 23552.1
A27: Wallace, Timothy | B27: Watson | C27: Facilities/Engineering | D27: Contract | E27: 35940 | G27: 88000 | H27: 5 | I27: =IF(OR(Table2[[#This Row],[Rating]]=4,Table2[[#This Row],[Rating]]=5), 0.05*Table2[[#This Row],[Salary]],0) -> 4400 | J27: =VLOOKUP(Table2[[#This Row],[Salary]],'Tax rates'!A$2:C$8, 2) + VLOOKUP(Table2[[#This Row],[Salary]],'Tax rates'!A$2:C$8, 3) * (Table2[[#This Row],[Salary]] - VLOOKUP(Table2[[#This Row],[Salary]],'Tax rates'!A$2:C$8,1)) -> 15409.5 | K27: =Table2[[#This Row],[Salary]]-Table2[[#This Row],[Taxes]] -> 72590.5 | L27: =Table2[[#This Row],[After tax salary]]+Table2[[#This Row],[Bonus]] -> 76990.5
A28: Booth, Raquel | B28: West | C28: Account Management | D28: Hourly | E28: 35946 | G28: 14332 | H28: 5 | I28: =IF(OR(Table2[[#This Row],[Rating]]=4,Table2[[#This Row],[Rating]]=5), 0.05*Table2[[#This Row],[Salary]],0) -> 716.6 | J28: =VLOOKUP(Table2[[#This Row],[Salary]],'Tax rates'!A$2:C$8, 2) + VLOOKUP(Table2[[#This Row],[Salary]],'Tax rates'!A$2:C$8, 3) * (Table2[[#This Row],[Salary]] - VLOOKUP(Table2[[#This Row],[Salary]],'Tax rates'!A$2:C$8,1)) -> 1529.34 | K28: =Table2[[#This Row],[Salary]]-Table2[[#This Row],[Taxes]] -> 12802.66 | L28: =Table2[[#This Row],[After tax salary]]+Table2[[#This Row],[Bonus]] -> 13519.26
A29: Jackson, Eric | B29: North | C29: Account Management | D29: Full Time | E29: 35958 | F29: R | G29: 61420 | H29: 4 | I29: =IF(OR(Table2[[#This Row],[Rating]]=4,Table2[[#This Row],[Rating]]=5), 0.05*Table2[[#This Row],[Salary]],0) -> 3071 | J29: =VLOOKUP(Table2[[#This Row],[Salary]],'Tax rates'!A$2:C$8, 2) + VLOOKUP(Table2[[#This Row],[Salary]],'Tax rates'!A$2:C$8, 3) * (Table2[[#This Row],[Salary]] - VLOOKUP(Table2[[#This Row],[Salary]],'Tax rates'!A$2:C$8,1)) -> 9451.9 | K29: =Table2[[#This Row],[Salary]]-Table2[[#This Row],[Taxes]] -> 51968.1 | L29: =Table2[[#This Row],[After tax salary]]+Table2[[#This Row],[Bonus]] -> 55039.1
A30: Roberson, Eileen | B30: Main | C30: Creative | D30: Contract | E30: 35959 | G30: 64470 | H30: 3 | I30: =IF(OR(Table2[[#This Row],[Rating]]=4,Table2[[#This Row],[Rating]]=5), 0.05*Table2[[#This Row],[Salary]],0) -> 0 | J30: =VLOOKUP(Table2[[#This Row],[Salary]],'Tax rates'!A$2:C$8, 2) + VLOOKUP(Table2[[#This Row],[Salary]],'Tax rates'!A$2:C$8, 3) * (Table2[[#This Row],[Salary]] - VLOOKUP(Table2[[#This Row],[Salary]],'Tax rates'!A$2:C$8,1)) -> 10122.9 | K30: =Table2[[#This Row],[Salary]]-Table2[[#This Row],[Taxes]] -> 54347.1 | L30: =Table2[[#This Row],[After tax salary]]+Table2[[#This Row],[Bonus]] -> 54347.1
A31: Owen, Robert | B31: Main | C31: Sales | D31: Half-Time | E31: 35961 | F31: DMR | G31: 20500 | H31: 3 | I31: =IF(OR(Table2[[#This Row],[Rating]]=4,Table2[[#This Row],[Rating]]=5), 0.05*Table2[[#This Row],[Salary]],0) -> 0 | J31: =VLOOKUP(Table2[[#This Row],[Salary]],'Tax rates'!A$2:C$8, 2) + VLOOKUP(Table2[[#This Row],[Salary]],'Tax rates'!A$2:C$8, 3) * (Table2[[#This Row],[Salary]] - VLOOKUP(Table2[[#This Row],[Salary]],'Tax rates'!A$2:C$8,1)) -> 2269.5 | K31: =Table2[[#This Row],[Salary]]-Table2[[#This Row],[Taxes]] -> 18230.5 | L31: =Table2[[#This Row],[After tax salary]]+Table2[[#This Row],[Bonus]] -> 18230.5
A32: Harding, Erin | B32: West | C32: Facilities/Engineering | D32: Full Time | E32: 35965 | F32: M | G32: 34780 | H32: 4 | I32: =IF(OR(Table2[[#This Row],[Rating]]=4,Table2[[#This Row],[Rating]]=5), 0.05*Table2[[#This Row],[Salary]],0) -> 1739 | J32: =VLOOKUP(Table2[[#This Row],[Salary]],'Tax rates'!A$2:C$8, 2) + VLOOKUP(Table2[[#This Row],[Salary]],'Tax rates'!A$2:C$8, 3) * (Table2[[#This Row],[Salary]] - VLOOKUP(Table2[[#This Row],[Salary]],'Tax rates'!A$2:C$8,1)) -> 3983.1 | K32: =Table2[[#This Row],[Salary]]-Table2[[#This Row],[Taxes]] -> 30796.9 | L32: =Table2[[#This Row],[After tax salary]]+Table2[[#This Row],[Bonus]] -> 32535.9
A33: Russell, Mark | B33: Main | C33: IT | D33: Full Time | E33: 35969 | F33: DMR | G33: 74530 | H33: 5 | I33: =IF(OR(Table2[[#This Row],[Rating]]=4,Table2[[#This Row],[Rating]]=5), 0.05*Table2[[#This Row],[Salary]],0) -> 3726.5 | J33: =VLOOKUP(Table2[[#This Row],[Salary]],'Tax rates'!A$2:C$8, 2) + VLOOKUP(Table2[[#This Row],[Salary]],'Tax rates'!A$2:C$8, 3) * (Table2[[#This Row],[Salary]] - VLOOKUP(Table2[[#This Row],[Salary]],'Tax rates'!A$2:C$8,1)) -> 12336.1 | K33: =Table2[[#This Row],[Salary]]-Table2[[#This Row],[Taxes]] -> 62193.9 | L33: =Table2[[#This Row],[After tax salary]]+Table2[[#This Row],[Bonus]] -> 65920.4
A34: Bradford, Raymond | B34: North | C34: Manufacturing | D34: Contract | E34: 35972 | G34: 71710 | H34: 5 | I34: =IF(OR(Table2[[#This Row],[Rating]]=4,Table2[[#This Row],[Rating]]=5), 0.05*Table2[[#This Row],[Salary]],0) -> 3585.5 | J34: =VLOOKUP(Table2[[#This Row],[Salary]],'Tax rates'!A$2:C$8, 2) + VLOOKUP(Table2[[#This Row],[Salary]],'Tax rates'!A$2:C$8, 3) * (Table2[[#This Row],[Salary]] - VLOOKUP(Table2[[#This Row],[Salary]],'Tax rates'!A$2:C$8,1)) -> 11715.7 | K34: =Table2[[#This Row],[Salary]]-Table2[[#This Row],[Taxes]] -> 59994.3 | L34: =Table2[[#This Row],[After tax salary]]+Table2[[#This Row],[Bonus]] -> 63579.8
A35: Atkins, Kevin | B35: North | C35: Manufacturing | D35: Hourly | E35: 35982 | G35: 8904 | H35: 3 | I35: =IF(OR(Table2[[#This Row],[Rating]]=4,Table2[[#This Row],[Rating]]=5), 0.05*Table2[[#This Row],[Salary]],0) -> 0 | J35: =VLOOKUP(Table2[[#This Row],[Salary]],'Tax rates'!A$2:C$8, 2) + VLOOKUP(Table2[[#This Row],[Salary]],'Tax rates'!A$2:C$8, 3) * (Table2[[#This Row],[Salary]] - VLOOKUP(Table2[[#This Row],[Salary]],'Tax rates'!A$2:C$8,1)) -> 890.4 | K35: =Table2[[#This Row],[Salary]]-Table2[[#This Row],[Taxes]] -> 8013.6 | L35: =Table2[[#This Row],[After tax salary]]+Table2[[#This Row],[Bonus]] -> 8013.6
A36: Santos, Garret | B36: Taft | C36: Product Development | D36: Full Time | E36: 35989 | F36: DM | G36: 71010 | H36: 5 | I36: =IF(OR(Table2[[#This Row],[Rating]]=4,Table2[[#This Row],[Rating]]=5), 0.05*Table2[[#This Row],[Salary]],0) -> 3550.5 | J36: =VLOOKUP(Table2[[#This Row],[Salary]],'Tax rates'!A$2:C$8, 2) + VLOOKUP(Table2[[#This Row],[Salary]],'Tax rates'!A$2:C$8, 3) * (Table2[[#This Row],[Salary]] - VLOOKUP(Table2[[#This Row],[Salary]],'Tax rates'!A$2:C$8,1)) -> 11561.7 | K36: =Table2[[#This Row],[Salary]]-Table2[[#This Row],[Taxes]] -> 59448.3 | L36: =Table2[[#This Row],[After tax salary]]+Table2[[#This Row],[Bonus]] -> 62998.8
A37: Preston, Chris | B37: Main | C37: Account Management | D37: Full Time | E37: 35990 | F37: D | G37: 36890 | H37: 1 | I37: =IF(OR(Table2[[#This Row],[Rating]]=4,Table2[[#This Row],[Rating]]=5), 0.05*Table2[[#This Row],[Salary]],0) -> 0 | J37: =VLOOKUP(Table2[[#This Row],[Salary]],'Tax rates'!A$2:C$8, 2) + VLOOKUP(Table2[[#This Row],[Salary]],'Tax rates'!A$2:C$8, 3) * (Table2[[#This Row],[Salary]] - VLOOKUP(Table2[[#This Row],[Salary]],'Tax rates'!A$2:C$8,1)) -> 4236.3 | K37: =Table2[[#This Row],[Salary]]-Table2[[#This Row],[Taxes]] -> 32653.7 | L37: =Table2[[#This Row],[After tax salary]]+Table2[[#This Row],[Bonus]] -> 32653.7
A38: Chambers, Richard | B38: Main | C38: Manufacturing | D38: Contract | E38: 35992 | G38: 68260 | H38: 5 | I38: =IF(OR(Table2[[#This Row],[Rating]]=4,Table2[[#This Row],[Rating]]=5), 0.05*Table2[[#This Row],[Salary]],0) -> 3413 | J38: =VLOOKUP(Table2[[#This Row],[Salary]],'Tax rates'!A$2:C$8, 2) + VLOOKUP(Table2[[#This Row],[Salary]],'Tax rates'!A$2:C$8, 3) * (Table2[[#This Row],[Salary]] - VLOOKUP(Table2[[#This Row],[Salary]],'Tax rates'!A$2:C$8,1)) -> 10956.7 | K38: =Table2[[#This Row],[Salary]]-Table2[[#This Row],[Taxes]] -> 57303.3 | L38: =Table2[[#This Row],[After tax salary]]+Table2[[#This Row],[Bonus]] -> 60716.3
A39: Jacobs, Florianne | B39: Main | C39: Manufacturing | D39: Full Time | E39: 35996 | F39: DMR | G39: 40340 | H39: 2 | I39: =IF(OR(Table2[[#This Row],[Rating]]=4,Table2[[#This Row],[Rating]]=5), 0.05*Table2[[#This Row],[Salary]],0) -> 0 | J39: =VLOOKUP(Table2[[#This Row],[Salary]],'Tax rates'!A$2:C$8, 2) + VLOOKUP(Table2[[#This Row],[Salary]],'Tax rates'!A$2:C$8, 3) * (Table2[[#This Row],[Salary]] - VLOOKUP(Table2[[#This Row],[Salary]],'Tax rates'!A$2:C$8,1)) -> 4814.3 | K39: =Table2[[#This Row],[Salary]]-Table2[[#This Row],[Taxes]] -> 35525.7 | L39: =Table2[[#This Row],[After tax salary]]+Table2[[#This Row],[Bonus]] -> 35525.7
A40: Wilkinson, Gregory | B40: North | C40: Manufacturing | D40: Contract | E40: 35997 | G40: 72520 | H40: 3 | I40: =IF(OR(Table2[[#This Row],[Rating]]=4,Table2[[#This Row],[Rating]]=5), 0.05*Table2[[#This Row],[Salary]],0) -> 0 | J40: =VLOOKUP(Table2[[#This Row],[Salary]],'Tax rates'!A$2:C$8, 2) + VLOOKUP(Table2[[#This Row],[Salary]],'Tax rates'!A$2:C$8, 3) * (Table2[[#This Row],[Salary]] - VLOOKUP(Table2[[#This Row],[Salary]],'Tax rates'!A$2:C$8,1)) -> 11893.9 | K40: =Table2[[#This Row],[Salary]]-Table2[[#This Row],[Taxes]] -> 60626.1 | L40: =Table2[[#This Row],[After tax salary]]+Table2[[#This Row],[Bonus]] -> 60626.1
A41: Stafford, Rhonda | B41: Main | C41: Manufacturing | D41: Full Time | E41: 36009 | F41: DMR | G41: 75120 | H41: 5 | I41: =IF(OR(Table2[[#This Row],[Rating]]=4,Table2[[#This Row],[Rating]]=5), 0.05*Table2[[#This Row],[Salary]],0) -> 3756 | J41: =VLOOKUP(Table2[[#This Row],[Salary]],'Tax rates'!A$2:C$8, 2) + VLOOKUP(Table2[[#This Row],[Salary]],'Tax rates'!A$2:C$8, 3) * (Table2[[#This Row],[Salary]] - VLOOKUP(Table2[[#This Row],[Salary]],'Tax rates'!A$2:C$8,1)) -> 12465.9 | K41: =Table2[[#This Row],[Salary]]-Table2[[#This Row],[Taxes]] -> 62654.1 | L41: =Table2[[#This Row],[After tax salary]]+Table2[[#This Row],[Bonus]] -> 66410.1
A42: Parker, Carl | B42: South | C42: Manufacturing | D42: Contract | E42: 36011 | G42: 45050 | H42: 1 | I42: =IF(OR(Table2[[#This Row],[Rating]]=4,Table2[[#This Row],[Rating]]=5), 0.05*Table2[[#This Row],[Salary]],0) -> 0 | J42: =VLOOKUP(Table2[[#This Row],[Salary]],'Tax rates'!A$2:C$8, 2) + VLOOKUP(Table2[[#This Row],[Salary]],'Tax rates'!A$2:C$8, 3) * (Table2[[#This Row],[Salary]] - VLOOKUP(Table2[[#This Row],[Salary]],'Tax rates'!A$2:C$8,1)) -> 5850.5 | K42: =Table2[[#This Row],[Salary]]-Table2[[#This Row],[Taxes]] -> 39199.5 | L42: =Table2[[#This Row],[After tax salary]]+Table2[[#This Row],[Bonus]] -> 39199.5
A43: Middleton, Jen | B43: Main | C43: Quality Assurance | D43: Full Time | E43: 36012 | F43: DM | G43: 78950 | H43: 1 | I43: =IF(OR(Table2[[#This Row],[Rating]]=4,Table2[[#This Row],[Rating]]=5), 0.05*Table2[[#This Row],[Salary]],0) -> 0 | J43: =VLOOKUP(Table2[[#This Row],[Salary]],'Tax rates'!A$2:C$8, 2) + VLOOKUP(Table2[[#This Row],[Salary]],'Tax rates'!A$2:C$8, 3) * (Table2[[#This Row],[Salary]] - VLOOKUP(Table2[[#This Row],[Salary]],'Tax rates'!A$2:C$8,1)) -> 13308.5 | K43: =Table2[[#This Row],[Salary]]-Table2[[#This Row],[Taxes]] -> 65641.5 | L43: =Table2[[#This Row],[After tax salary]]+Table2[[#This Row],[Bonus]] -> 65641.5
A44: Crawford, Ronald | B44: North | C44: Quality Control | D44: Full Time | E44: 36025 | F44: DM | G44: 64470 | H44: 5 | I44: =IF(OR(Table2[[#This Row],[Rating]]=4,Table2[[#This Row],[Rating]]=5), 0.05*Table2[[#This Row],[Salary]],0) -> 3223.5 | J44: =VLOOKUP(Table2[[#This Row],[Salary]],'Tax rates'!A$2:C$8, 2) + VLOOKUP(Table2[[#This Row],[Salary]],'Tax rates'!A$2:C$8, 3) * (Table2[[#This Row],[Salary]] - VLOOKUP(Table2[[#This Row],[Salary]],'Tax rates'!A$2:C$8,1)) -> 10122.9 | K44: =Table2[[#This Row],[Salary]]-Table2[[#This Row],[Taxes]] -> 54347.1 | L44: =Table2[[#This Row],[After tax salary]]+Table2[[#This Row],[Bonus]] -> 57570.6
A45: Andrews, Diane | B45: North | C45: Account Management | D45: Hourly | E45: 36028 | G45: 16688 | H45: 3 | I45: =IF(OR(Table2[[#This Row],[Rating]]=4,Table2[[#This Row],[Rating]]=5), 0.05*Table2[[#This Row],[Salary]],0) -> 0 | J45: =VLOOKUP(Table2[[#This Row],[Salary]],'Tax rates'!A$2:C$8, 2) + VLOOKUP(Table2[[#This Row],[Salary]],'Tax rates'!A$2:C$8, 3) * (Table2[[#This Row],[Salary]] - VLOOKUP(Table2[[#This Row],[Salary]],'Tax rates'!A$2:C$8,1)) -> 1812.06 | K45: =Table2[[#This Row],[Salary]]-Table2[[#This Row],[Taxes]] -> 14875.94 | L45: =Table2[[#This Row],[After tax salary]]+Table2[[#This Row],[Bonus]] -> 14875.94
A46: Conway, Brett | B46: South | C46: Facilities/Engineering | D46: Contract | E46: 36038 | G46: 30340 | H46: 3 | I46: =IF(OR(Table2[[#This Row],[Rating]]=4,Table2[[#This Row],[Rating]]=5), 0.05*Table2[[#This Row],[Salary]],0) -> 0 | J46: =VLOOKUP(Table2[[#This Row],[Salary]],'Tax rates'!A$2:C$8, 2) + VLOOKUP(Table2[[#This Row],[Salary]],'Tax rates'!A$2:C$8, 3) * (Table2[[#This Row],[Salary]] - VLOOKUP(Table2[[#This Row],[Salary]],'Tax rates'!A$2:C$8,1)) -> 3450.3 | K46: =Table2[[#This Row],[Salary]]-Table2[[#This Row],[Taxes]] -> 26889.7 | L46: =Table2[[#This Row],[After tax salary]]+Table2[[#This Row],[Bonus]] -> 26889.7
A47: McCarthy, Ryan | B47: West | C47: Sales | D47: Contract | E47: 36047 | G47: 72480 | H47: 2 | I47: =IF(OR(Table2[[#This Row],[Rating]]=4,Table2[[#This Row],[Rating]]=5), 0.05*Table2[[#This Row],[Salary]],0) -> 0 | J47: =VLOOKUP(Table2[[#This Row],[Salary]],'Tax rates'!A$2:C$8, 2) + VLOOKUP(Table2[[#This Row],[Salary]],'Tax rates'!A$2:C$8, 3) * (Table2[[#This Row],[Salary]] - VLOOKUP(Table2[[#This Row],[Salary]],'Tax rates'!A$2:C$8,1)) -> 11885.1 | K47: =Table2[[#This Row],[Salary]]-Table2[[#This Row],[Taxes]] -> 60594.9 | L47: =Table2[[#This Row],[After tax salary]]+Table2[[#This Row],[Bonus]] -> 60594.9
A48: Cruz, Janene | B48: South | C48: Quality Control | D48: Half-Time | E48: 36053 | F48: D | G48: 46105 | H48: 5 | I48: =IF(OR(Table2[[#This Row],[Rating]]=4,Table2[[#This Row],[Rating]]=5), 0.05*Table2[[#This Row],[Salary]],0) -> 2305.25 | J48: =VLOOKUP(Table2[[#This Row],[Salary]],'Tax rates'!A$2:C$8, 2) + VLOOKUP(Table2[[#This Row],[Salary]],'Tax rates'!A$2:C$8, 3) * (Table2[[#This Row],[Salary]] - VLOOKUP(Table2[[#This Row],[Salary]],'Tax rates'!A$2:C$8,1)) -> 6082.6 | K48: =Table2[[#This Row],[Salary]]-Table2[[#This Row],[Taxes]] -> 40022.4 | L48: =Table2[[#This Row],[After tax salary]]+Table2[[#This Row],[Bonus]] -> 42327.65
A49: Mendoza, Bobby | B49: West | C49: Facilities/Engineering | D49: Hourly | E49: 36059 | G49: 18500 | H49: 5 | I49: =IF(OR(Table2[[#This Row],[Rating]]=4,Table2[[#This Row],[Rating]]=5), 0.05*Table2[[#This Row],[Salary]],0) -> 925 | J49: =VLOOKUP(Table2[[#This Row],[Salary]],'Tax rates'!A$2:C$8, 2) + VLOOKUP(Table2[[#This Row],[Salary]],'Tax rates'!A$2:C$8, 3) * (Table2[[#This Row],[Salary]] - VLOOKUP(Table2[[#This Row],[Salary]],'Tax rates'!A$2:C$8,1)) -> 2029.5 | K49: =Table2[[#This Row],[Salary]]-Table2[[#This Row],[Taxes]] -> 16470.5 | L49: =Table2[[#This Row],[After tax salary]]+Table2[[#This Row],[Bonus]] -> 17395.5
A50: Pena, Erik | B50: South | C50: Manufacturing | D50: Hourly | E50: 36067 | G50: 37612 | H50: 4 | I50: =IF(OR(Table2[[#This Row],[Rating]]=4,Table2[[#This Row],[Rating]]=5), 0.05*Table2[[#This Row],[Salary]],0) -> 1880.6 | J50: =VLOOKUP(Table2[[#This Row],[Salary]],'Tax rates'!A$2:C$8, 2) + VLOOKUP(Table2[[#This Row],[Salary]],'Tax rates'!A$2:C$8, 3) * (Table2[[#This Row],[Salary]] - VLOOKUP(Table2[[#This Row],[Salary]],'Tax rates'!A$2:C$8,1)) -> 4322.94 | K50: =Table2[[#This Row],[Salary]]-Table2[[#This Row],[Taxes]] -> 33289.06 | L50: =Table2[[#This Row],[After tax salary]]+Table2[[#This Row],[Bonus]] -> 35169.66
A51: McCormick, Hsi | B51: West | C51: Quality Assurance | D51: Contract | E51: 36070 | G51: 59050 | H51: 4 | I51: =IF(OR(Table2[[#This Row],[Rating]]=4,Table2[[#This Row],[Rating]]=5), 0.05*Table2[[#This Row],[Salary]],0) -> 2952.5 | J51: =VLOOKUP(Table2[[#This Row],[Salary]],'Tax rates'!A$2:C$8, 2) + VLOOKUP(Table2[[#This Row],[Salary]],'Tax rates'!A$2:C$8, 3) * (Table2[[#This Row],[Salary]] - VLOOKUP(Table2[[#This Row],[Salary]],'Tax rates'!A$2:C$8,1)) -> 8930.5 | K51: =Table2[[#This Row],[Salary]]-Table2[[#This Row],[Taxes]] -> 50119.5 | L51: =Table2[[#This Row],[After tax salary]]+Table2[[#This Row],[Bonus]] -> 53072
A52: McDowell, Scott | B52: Main | C52: Creative | D52: Full Time | E52: 36077 | F52: R | G52: 50110 | H52: 1 | I52: =IF(OR(Table2[[#This Row],[Rating]]=4,Table2[[#This Row],[Rating]]=5), 0.05*Table2[[#This Row],[Salary]],0) -> 0 | J52: =VLOOKUP(Table2[[#This Row],[Salary]],'Tax rates'!A$2:C$8, 2) + VLOOKUP(Table2[[#This Row],[Salary]],'Tax rates'!A$2:C$8, 3) * (Table2[[#This Row],[Salary]] - VLOOKUP(Table2[[#This Row],[Salary]],'Tax rates'!A$2:C$8,1)) -> 6963.7 | K52: =Table2[[#This Row],[Salary]]-Table2[[#This Row],[Taxes]] -> 43146.3 | L52: =Table2[[#This Row],[After tax salary]]+Table2[[#This Row],[Bonus]] -> 43146.3
A53: Miles, Kenneth | B53: Main | C53: Quality Assurance | D53: Full Time | E53: 36078 | F53: D | G53: 79610 | H53: 2 | I53: =IF(OR(Table2[[#This Row],[Rating]]=4,Table2[[#This Row],[Rating]]=5), 0.05*Table2[[#This Row],[Salary]],0) -> 0 | J53: =VLOOKUP(Table2[[#This Row],[Salary]],'Tax rates'!A$2:C$8, 2) + VLOOKUP(Table2[[#This Row],[Salary]],'Tax rates'!A$2:C$8, 3) * (Table2[[#This Row],[Salary]] - VLOOKUP(Table2[[#This Row],[Salary]],'Tax rates'!A$2:C$8,1)) -> 13453.7 | K53: =Table2[[#This Row],[Salary]]-Table2[[#This Row],[Taxes]] -> 66156.3 | L53: =Table2[[#This Row],[After tax salary]]+Table2[[#This Row],[Bonus]] -> 66156.3
A54: Thomas, Shannon | B54: Taft | C54: Quality Control | D54: Full Time | E54: 36080 | F54: R | G54: 48410 | H54: 5 | I54: =IF(OR(Table2[[#This Row],[Rating]]=4,Table2[[#This Row],[Rating]]=5), 0.05*Table2[[#This Row],[Salary]],0) -> 2420.5 | J54: =VLOOKUP(Table2[[#This Row],[Salary]],'Tax rates'!A$2:C$8, 2) + VLOOKUP(Table2[[#This Row],[Salary]],'Tax rates'!A$2:C$8, 3) * (Table2[[#This Row],[Salary]] - VLOOKUP(Table2[[#This Row],[Salary]],'Tax rates'!A$2:C$8,1)) -> 6589.7 | K54: =Table2[[#This Row],[Salary]]-Table2[[#This Row],[Taxes]] -> 41820.3 | L54: =Table2[[#This Row],[After tax salary]]+Table2[[#This Row],[Bonus]] -> 44240.8
A55: Massey, Mark | B55: West | C55: Quality Assurance | D55: Full Time | E55: 36081 | F55: R | G55: 67407 | H55: 5 | I55: =IF(OR(Table2[[#This Row],[Rating]]=4,Table2[[#This Row],[Rating]]=5), 0.05*Table2[[#This Row],[Salary]],0) -> 3370.35 | J55: =VLOOKUP(Table2[[#This Row],[Salary]],'Tax rates'!A$2:C$8, 2) + VLOOKUP(Table2[[#This Row],[Salary]],'Tax rates'!A$2:C$8, 3) * (Table2[[#This Row],[Salary]] - VLOOKUP(Table2[[#This Row],[Salary]],'Tax rates'!A$2:C$8,1)) -> 10769.04 | K55: =Table2[[#This Row],[Salary]]-Table2[[#This Row],[Taxes]] -> 56637.96 | L55: =Table2[[#This Row],[After tax salary]]+Table2[[#This Row],[Bonus]] -> 60008.31
A56: Chen, Jaime | B56: Taft | C56: Product Development | D56: Full Time | E56: 36082 | F56: R | G56: 82400 | H56: 2 | I56: =IF(OR(Table2[[#This Row],[Rating]]=4,Table2[[#This Row],[Rating]]=5), 0.05*Table2[[#This Row],[Salary]],0) -> 0 | J56: =VLOOKUP(Table2[[#This Row],[Salary]],'Tax rates'!A$2:C$8, 2) + VLOOKUP(Table2[[#This Row],[Salary]],'Tax rates'!A$2:C$8, 3) * (Table2[[#This Row],[Salary]] - VLOOKUP(Table2[[#This Row],[Salary]],'Tax rates'!A$2:C$8,1)) -> 14067.5 | K56: =Table2[[#This Row],[Salary]]-Table2[[#This Row],[Taxes]] -> 68332.5 | L56: =Table2[[#This Row],[After tax salary]]+Table2[[#This Row],[Bonus]] -> 68332.5
A57: Pope, Duane | B57: Main | C57: Sales | D57: Hourly | E57: 36084 | G57: 21668 | H57: 4 | I57: =IF(OR(Table2[[#This Row],[Rating]]=4,Table2[[#This Row],[Rating]]=5), 0.05*Table2[[#This Row],[Salary]],0) -> 1083.4 | J57: =VLOOKUP(Table2[[#This Row],[Salary]],'Tax rates'!A$2:C$8, 2) + VLOOKUP(Table2[[#This Row],[Salary]],'Tax rates'!A$2:C$8, 3) * (Table2[[#This Row],[Salary]] - VLOOKUP(Table2[[#This Row],[Salary]],'Tax rates'!A$2:C$8,1)) -> 2409.66 | K57: =Table2[[#This Row],[Salary]]-Table2[[#This Row],[Taxes]] -> 19258.34 | L57: =Table2[[#This Row],[After tax salary]]+Table2[[#This Row],[Bonus]] -> 20341.74
A58: Chapman, Jessica | B58: North | C58: Account Management | D58: Half-Time | E58: 36084 | F58: DM | G58: 45750 | H58: 5 | I58: =IF(OR(Table2[[#This Row],[Rating]]=4,Table2[[#This Row],[Rating]]=5), 0.05*Table2[[#This Row],[Salary]],0) -> 2287.5 | J58: =VLOOKUP(Table2[[#This Row],[Salary]],'Tax rates'!A$2:C$8, 2) + VLOOKUP(Table2[[#This Row],[Salary]],'Tax rates'!A$2:C$8, 3) * (Table2[[#This Row],[Salary]] - VLOOKUP(Table2[[#This Row],[Salary]],'Tax rates'!A$2:C$8,1)) -> 6004.5 | K58: =Table2[[#This Row],[Salary]]-Table2[[#This Row],[Taxes]] -> 39745.5 | L58: =Table2[[#This Row],[After tax salary]]+Table2[[#This Row],[Bonus]] -> 42033
A59: Decker, Amy | B59: South | C59: Manufacturing | D59: Full Time | E59: 36084 | F59: DMR | G59: 33210 | H59: 4 | I59: =IF(OR(Table2[[#This Row],[Rating]]=4,Table2[[#This Row],[Rating]]=5), 0.05*Table2[[#This Row],[Salary]],0) -> 1660.5 | J59: =VLOOKUP(Table2[[#This Row],[Salary]],'Tax rates'!A$2:C$8, 2) + VLOOKUP(Table2[[#This Row],[Salary]],'Tax rates'!A$2:C$8, 3) * (Table2[[#This Row],[Salary]] - VLOOKUP(Table2[[#This Row],[Salary]],'Tax rates'!A$2:C$8,1)) -> 3794.7 | K59: =Table2[[#This Row],[Salary]]-Table2[[#This Row],[Taxes]] -> 29415.3 | L59: =Table2[[#This Row],[After tax salary]]+Table2[[#This Row],[Bonus]] -> 31075.8
A60: Bowman, Michael | B60: West | C60: Account Management | D60: Contract | E60: 36086 | G60: 47520 | H60: 1 | I60: =IF(OR(Table2[[#This Row],[Rating]]=4,Table2[[#This Row],[Rating]]=5), 0.05*Table2[[#This Row],[Salary]],0) -> 0 | J60: =VLOOKUP(Table2[[#This Row],[Salary]],'Tax rates'!A$2:C$8, 2) + VLOOKUP(Table2[[#This Row],[Salary]],'Tax rates'!A$2:C$8, 3) * (Table2[[#This Row],[Salary]] - VLOOKUP(Table2[[#This Row],[Salary]],'Tax rates'!A$2:C$8,1)) -> 6393.9 | K60: =Table2[[#This Row],[Salary]]-Table2[[#This Row],[Taxes]] -> 41126.1 | L60: =Table2[[#This Row],[After tax salary]]+Table2[[#This Row],[Bonus]] -> 41126.1
A61: Perry, Christopher | B61: West | C61: Facilities/Engineering | D61: Contract | E61: 36087 | G61: 76930 | H61: 1 | I61: =IF(OR(Table2[[#This Row],[Rating]]=4,Table2[[#This Row],[Rating]]=5), 0.05*Table2[[#This Row],[Salary]],0) -> 0 | J61: =VLOOKUP(Table2[[#This Row],[Salary]],'Tax rates'!A$2:C$8, 2) + VLOOKUP(Table2[[#This Row],[Salary]],'Tax rates'!A$2:C$8, 3) * (Table2[[#This Row],[Salary]] - VLOOKUP(Table2[[#This Row],[Salary]],'Tax rates'!A$2:C$8,1)) -> 12864.1 | K61: =Table2[[#This Row],[Salary]]-Table2[[#This Row],[Taxes]] -> 64065.9 | L61: =Table2[[#This Row],[After tax salary]]+Table2[[#This Row],[Bonus]] -> 64065.9
A62: Moses, Mark | B62: Main | C62: Account Management | D62: Full Time | E62: 36088 | F62: M | G62: 54580 | H62: 4 | I62: =IF(OR(Table2[[#This Row],[Rating]]=4,Table2[[#This Row],[Rating]]=5), 0.05*Table2[[#This Row],[Salary]],0) -> 2729 | J62: =VLOOKUP(Table2[[#This Row],[Salary]],'Tax rates'!A$2:C$8, 2) + VLOOKUP(Table2[[#This Row],[Salary]],'Tax rates'!A$2:C$8, 3) * (Table2[[#This Row],[Salary]] - VLOOKUP(Table2[[#This Row],[Salary]],'Tax rates'!A$2:C$8,1)) -> 7947.1 | K62: =Table2[[#This Row],[Salary]]-Table2[[#This Row],[Taxes]] -> 46632.9 | L62: =Table2[[#This Row],[After tax salary]]+Table2[[#This Row],[Bonus]] -> 49361.9
A63: Waters, Alfred | B63: North | C63: Marketing | D63: Half-Time | E63: 36094 | F63: DMR | G63: 47885 | H63: 1 | I63: =IF(OR(Table2[[#This Row],[Rating]]=4,Table2[[#This Row],[Rating]]=5), 0.05*Table2[[#This Row],[Salary]],0) -> 0 | J63: =VLOOKUP(Table2[[#This Row],[Salary]],'Tax rates'!A$2:C$8, 2) + VLOOKUP(Table2[[#This Row],[Salary]],'Tax rates'!A$2:C$8, 3) * (Table2[[#This Row],[Salary]] - VLOOKUP(Table2[[#This Row],[Salary]],'Tax rates'!A$2:C$8,1)) -> 6474.2 | K63: =Table2[[#This Row],[Salary]]-Table2[[#This Row],[Taxes]] -> 41410.8 | L63: =Table2[[#This Row],[After tax salary]]+Table2[[#This Row],[Bonus]] -> 41410.8
A64: Parrish, Debra | B64: Main | C64: Manufacturing | D64: Full Time | E64: 36101 | F64: DMR | G64: 88240 | H64: 5 | I64: =IF(OR(Table2[[#This Row],[Rating]]=4,Table2[[#This Row],[Rating]]=5), 0.05*Table2[[#This Row],[Salary]],0) -> 4412 | J64: =VLOOKUP(Table2[[#This Row],[Salary]],'Tax rates'!A$2:C$8, 2) + VLOOKUP(Table2[[#This Row],[Salary]],'Tax rates'!A$2:C$8, 3) * (Table2[[#This Row],[Salary]] - VLOOKUP(Table2[[#This Row],[Salary]],'Tax rates'!A$2:C$8,1)) -> 15467.1 | K64: =Table2[[#This Row],[Salary]]-Table2[[#This Row],[Taxes]] -> 72772.9 | L64: =Table2[[#This Row],[After tax salary]]+Table2[[#This Row],[Bonus]] -> 77184.9
A65: Barr, Jennifer | B65: North | C65: Marketing | D65: Full Time | E65: 36116 | F65: D | G65: 49770 | H65: 1 | I65: =IF(OR(Table2[[#This Row],[Rating]]=4,Table2[[#This Row],[Rating]]=5), 0.05*Table2[[#This Row],[Salary]],0) -> 0 | J65: =VLOOKUP(Table2[[#This Row],[Salary]],'Tax rates'!A$2:C$8, 2) + VLOOKUP(Table2[[#This Row],[Salary]],'Tax rates'!A$2:C$8, 3) * (Table2[[#This Row],[Salary]] - VLOOKUP(Table2[[#This Row],[Salary]],'Tax rates'!A$2:C$8,1)) -> 6888.9 | K65: =Table2[[#This Row],[Salary]]-Table2[[#This Row],[Taxes]] -> 42881.1 | L65: =Table2[[#This Row],[After tax salary]]+Table2[[#This Row],[Bonus]] -> 42881.1
A66: Jensen, Kristina | B66: West | C66: Marketing | D66: Half-Time | E66: 36121 | F66: R | G66: 28880 | H66: 3 | I66: =IF(OR(Table2[[#This Row],[Rating]]=4,Table2[[#This Row],[Rating]]=5), 0.05*Table2[[#This Row],[Salary]],0) -> 0 | J66: =VLOOKUP(Table2[[#This Row],[Salary]],'Tax rates'!A$2:C$8, 2) + VLOOKUP(Table2[[#This Row],[Salary]],'Tax rates'!A$2:C$8, 3) * (Table2[[#This Row],[Salary]] - VLOOKUP(Table2[[#This Row],[Salary]],'Tax rates'!A$2:C$8,1)) -> 3275.1 | K66: =Table2[[#This Row],[Salary]]-Table2[[#This Row],[Taxes]] -> 25604.9 | L66: =Table2[[#This Row],[After tax salary]]+Table2[[#This Row],[Bonus]] -> 25604.9
A67: Carson, Anthony | B67: West | C67: Manufacturing | D67: Full Time | E67: 36122 | F67: DM | G67: 22660 | H67: 2 | I67: =IF(OR(Table2[[#This Row],[Rating]]=4,Table2[[#This Row],[Rating]]=5), 0.05*Table2[[#This Row],[Salary]],0) -> 0 | J67: =VLOOKUP(Table2[[#This Row],[Salary]],'Tax rates'!A$2:C$8, 2) + VLOOKUP(Table2[[#This Row],[Salary]],'Tax rates'!A$2:C$8, 3) * (Table2[[#This Row],[Salary]] - VLOOKUP(Table2[[#This Row],[Salary]],'Tax rates'!A$2:C$8,1)) -> 2528.7 | K67: =Table2[[#This Row],[Salary]]-Table2[[#This Row],[Taxes]] -> 20131.3 | L67: =Table2[[#This Row],[After tax salary]]+Table2[[#This Row],[Bonus]] -> 20131.3
A68: Doyle, Leslie | B68: Taft | C68: Account Management | D68: Full Time | E68: 36136 | F68: R | G68: 45000 | H68: 4 | I68: =IF(OR(Table2[[#This Row],[Rating]]=4,Table2[[#This Row],[Rating]]=5), 0.05*Table2[[#This Row],[Salary]],0) -> 2250 | J68: =VLOOKUP(Table2[[#This Row],[Salary]],'Tax rates'!A$2:C$8, 2) + VLOOKUP(Table2[[#This Row],[Salary]],'Tax rates'!A$2:C$8, 3) * (Table2[[#This Row],[Salary]] - VLOOKUP(Table2[[#This Row],[Salary]],'Tax rates'!A$2:C$8,1)) -> 5839.5 | K68: =Table2[[#This Row],[Salary]]-Table2[[#This Row],[Taxes]] -> 39160.5 | L68: =Table2[[#This Row],[After tax salary]]+Table2[[#This Row],[Bonus]] -> 41410.5
A69: Wolf, Debbie | B69: Taft | C69: Training | D69: Full Time | E69: 36143 | F69: R | G69: 72090 | H69: 5 | I69: =IF(OR(Table2[[#This Row],[Rating]]=4,Table2[[#This Row],[Rating]]=5), 0.05*Table2[[#This Row],[Salary]],0) -> 3604.5 | J69: =VLOOKUP(Table2[[#This Row],[Salary]],'Tax rates'!A$2:C$8, 2) + VLOOKUP(Table2[[#This Row],[Salary]],'Tax rates'!A$2:C$8, 3) * (Table2[[#This Row],[Salary]] - VLOOKUP(Table2[[#This Row],[Salary]],'Tax rates'!A$2:C$8,1)) -> 11799.3 | K69: =Table2[[#This Row],[Salary]]-Table2[[#This Row],[Taxes]] -> 60290.7 | L69: =Table2[[#This Row],[After tax salary]]+Table2[[#This Row],[Bonus]] -> 63895.2
A70: Moore, Robert | B70: West | C70: Marketing | D70: Full Time | E70: 36145 | F70: DM | G70: 31260 | H70: 5 | I70: =IF(OR(Table2[[#This Row],[Rating]]=4,Table2[[#This Row],[Rating]]=5), 0.05*Table2[[#This Row],[Salary]],0) -> 1563 | J70: =VLOOKUP(Table2[[#This Row],[Salary]],'Tax rates'!A$2:C$8, 2) + VLOOKUP(Table2[[#This Row],[Salary]],'Tax rates'!A$2:C$8, 3) * (Table2[[#This Row],[Salary]] - VLOOKUP(Table2[[#This Row],[Salary]],'Tax rates'!A$2:C$8,1)) -> 3560.7 | K70: =Table2[[#This Row],[Salary]]-Table2[[#This Row],[Taxes]] -> 27699.3 | L70: =Table2[[#This Row],[After tax salary]]+Table2[[#This Row],[Bonus]] -> 29262.3
A71: Page, Lisa | B71: West | C71: ADC | D71: Full Time | E71: 36171 | F71: DMR | G71: 54550 | H71: 1 | I71: =IF(OR(Table2[[#This Row],[Rating]]=4,Table2[[#This Row],[Rating]]=5), 0.05*Table2[[#This Row],[Salary]],0) -> 0 | J71: =VLOOKUP(Table2[[#This Row],[Salary]],'Tax rates'!A$2:C$8, 2) + VLOOKUP(Table2[[#This Row],[Salary]],'Tax rates'!A$2:C$8, 3) * (Table2[[#This Row],[Salary]] - VLOOKUP(Table2[[#This Row],[Salary]],'Tax rates'!A$2:C$8,1)) -> 7940.5 | K71: =Table2[[#This Row],[Salary]]-Table2[[#This Row],[Taxes]] -> 46609.5 | L71: =Table2[[#This Row],[After tax salary]]+Table2[[#This Row],[Bonus]] -> 46609.5
A72: Leon, Emily | B72: Main | C72: Sales | D72: Full Time | E72: 36175 | F72: R | G72: 23520 | H72: 2 | I72: =IF(OR(Table2[[#This Row],[Rating]]=4,Table2[[#This Row],[Rating]]=5), 0.05*Table2[[#This Row],[Salary]],0) -> 0 | J72: =VLOOKUP(Table2[[#This Row],[Salary]],'Tax rates'!A$2:C$8, 2) + VLOOKUP(Table2[[#This Row],[Salary]],'Tax rates'!A$2:C$8, 3) * (Table2[[#This Row],[Salary]] - VLOOKUP(Table2[[#This Row],[Salary]],'Tax rates'!A$2:C$8,1)) -> 2631.9 | K72: =Table2[[#This Row],[Salary]]-Table2[[#This Row],[Taxes]] -> 20888.1 | L72: =Table2[[#This Row],[After tax salary]]+Table2[[#This Row],[Bonus]] -> 20888.1
A73: Maxwell, Jill | B73: Taft | C73: Creative | D73: Contract | E73: 36176 | G73: 32940 | H73: 5 | I73: =IF(OR(Table2[[#This Row],[Rating]]=4,Table2[[#This Row],[Rating]]=5), 0.05*Table2[[#This Row],[Salary]],0) -> 1647 | J73: =VLOOKUP(Table2[[#This Row],[Salary]],'Tax rates'!A$2:C$8, 2) + VLOOKUP(Table2[[#This Row],[Salary]],'Tax rates'!A$2:C$8, 3) * (Table2[[#This Row],[Salary]] - VLOOKUP(Table2[[#This Row],[Salary]],'Tax rates'!A$2:C$8,1)) -> 3762.3 | K73: =Table2[[#This Row],[Salary]]-Table2[[#This Row],[Taxes]] -> 29177.7 | L73: =Table2[[#This Row],[After tax salary]]+Table2[[#This Row],[Bonus]] -> 30824.7
A74: Mercado, David | B74: Main | C74: Manufacturing | D74: Half-Time | E74: 36177 | F74: M | G74: 21670 | H74: 2 | I74: =IF(OR(Table2[[#This Row],[Rating]]=4,Table2[[#This Row],[Rating]]=5), 0.05*Table2[[#This Row],[Salary]],0) -> 0 | J74: =VLOOKUP(Table2[[#This Row],[Salary]],'Tax rates'!A$2:C$8, 2) + VLOOKUP(Table2[[#This Row],[Salary]],'Tax rates'!A$2:C$8, 3) * (Table2[[#This Row],[Salary]] - VLOOKUP(Table2[[#This Row],[Salary]],'Tax rates'!A$2:C$8,1)) -> 2409.9 | K74: =Table2[[#This Row],[Salary]]-Table2[[#This Row],[Taxes]] -> 19260.1 | L74: =Table2[[#This Row],[After tax salary]]+Table2[[#This Row],[Bonus]] -> 19260.1
A75: Gomez, Ed | B75: South | C75: Environmental Health/Safety | D75: Full Time | E75: 36182 | F75: R | G75: 68300 | H75: 5 | I75: =IF(OR(Table2[[#This Row],[Rating]]=4,Table2[[#This Row],[Rating]]=5), 0.05*Table2[[#This Row],[Salary]],0) -> 3415 | J75: =VLOOKUP(Table2[[#This Row],[Salary]],'Tax rates'!A$2:C$8, 2) + VLOOKUP(Table2[[#This Row],[Salary]],'Tax rates'!A$2:C$8, 3) * (Table2[[#This Row],[Salary]] - VLOOKUP(Table2[[#This Row],[Salary]],'Tax rates'!A$2:C$8,1)) -> 10965.5 | K75: =Table2[[#This Row],[Salary]]-Table2[[#This Row],[Taxes]] -> 57334.5 | L75: =Table2[[#This Row],[After tax salary]]+Table2[[#This Row],[Bonus]] -> 60749.5
A76: Marquez, Thomas | B76: West | C76: Marketing | D76: Contract | E76: 36192 | G76: 47620 | H76: 5 | I76: =IF(OR(Table2[[#This Row],[Rating]]=4,Table2[[#This Row],[Rating]]=5), 0.05*Table2[[#This Row],[Salary]],0) -> 2381 | J76: =VLOOKUP(Table2[[#This Row],[Salary]],'Tax rates'!A$2:C$8, 2) + VLOOKUP(Table2[[#This Row],[Salary]],'Tax rates'!A$2:C$8, 3) * (Table2[[#This Row],[Salary]] - VLOOKUP(Table2[[#This Row],[Salary]],'Tax rates'!A$2:C$8,1)) -> 6415.9 | K76: =Table2[[#This Row],[Salary]]-Table2[[#This Row],[Taxes]] -> 41204.1 | L76: =Table2[[#This Row],[After tax salary]]+Table2[[#This Row],[Bonus]] -> 43585.1
A77: Blackwell, Brandon | B77: West | C77: Quality Control | D77: Contract | E77: 36193 | G77: 58250 | H77: 2 | I77: =IF(OR(Table2[[#This Row],[Rating]]=4,Table2[[#This Row],[Rating]]=5), 0.05*Table2[[#This Row],[Salary]],0) -> 0 | J77: =VLOOKUP(Table2[[#This Row],[Salary]],'Tax rates'!A$2:C$8, 2) + VLOOKUP(Table2[[#This Row],[Salary]],'Tax rates'!A$2:C$8, 3) * (Table2[[#This Row],[Salary]] - VLOOKUP(Table2[[#This Row],[Salary]],'Tax rates'!A$2:C$8,1)) -> 8754.5 | K77: =Table2[[#This Row],[Salary]]-Table2[[#This Row],[Taxes]] -> 49495.5 | L77: =Table2[[#This Row],[After tax salary]]+Table2[[#This Row],[Bonus]] -> 49495.5
A78: Carter, Allan | B78: Main | C78: Account Management | D78: Full Time | E78: 36195 | F78: M | G78: 46360 | H78: 5 | I78: =IF(OR(Table2[[#This Row],[Rating]]=4,Table2[[#This Row],[Rating]]=5), 0.05*Table2[[#This Row],[Salary]],0) -> 2318 | J78: =VLOOKUP(Table2[[#This Row],[Salary]],'Tax rates'!A$2:C$8, 2) + VLOOKUP(Table2[[#This Row],[Salary]],'Tax rates'!A$2:C$8, 3) * (Table2[[#This Row],[Salary]] - VLOOKUP(Table2[[#This Row],[Salary]],'Tax rates'!A$2:C$8,1)) -> 6138.7 | K78: =Table2[[#This Row],[Salary]]-Table2[[#This Row],[Taxes]] -> 40221.3 | L78: =Table2[[#This Row],[After tax salary]]+Table2[[#This Row],[Bonus]] -> 42539.3
A79: McDaniel, Tamara | B79: Main | C79: Quality Assurance | D79: Half-Time | E79: 36196 | F79: DMR | G79: 34980 | H79: 2 | I79: =IF(OR(Table2[[#This Row],[Rating]]=4,Table2[[#This Row],[Rating]]=5), 0.05*Table2[[#This Row],[Salary]],0) -> 0 | J79: =VLOOKUP(Table2[[#This Row],[Salary]],'Tax rates'!A$2:C$8, 2) + VLOOKUP(Table2[[#This Row],[Salary]],'Tax rates'!A$2:C$8, 3) * (Table2[[#This Row],[Salary]] - VLOOKUP(Table2[[#This Row],[Salary]],'Tax rates'!A$2:C$8,1)) -> 4007.1 | K79: =Table2[[#This Row],[Salary]]-Table2[[#This Row],[Taxes]] -> 30972.9 | L79: =Table2[[#This Row],[After tax salary]]+Table2[[#This Row],[Bonus]] -> 30972.9
A80: Butler, Roy | B80: Taft | C80: Manufacturing | D80: Full Time | E80: 36198 | F80: D | G80: 81400 | H80: 2 | I80: =IF(OR(Table2[[#This Row],[Rating]]=4,Table2[[#This Row],[Rating]]=5), 0.05*Table2[[#This Row],[Salary]],0) -> 0 | J80: =VLOOKUP(Table2[[#This Row],[Salary]],'Tax rates'!A$2:C$8, 2) + VLOOKUP(Table2[[#This Row],[Salary]],'Tax rates'!A$2:C$8, 3) * (Table2[[#This Row],[Salary]] - VLOOKUP(Table2[[#This Row],[Salary]],'Tax rates'!A$2:C$8,1)) -> 13847.5 | K80: =Table2[[#This Row],[Salary]]-Table2[[#This Row],[Taxes]] -> 67552.5 | L80: =Table2[[#This Row],[After tax salary]]+Table2[[#This Row],[Bonus]] -> 67552.5
A81: Reyes, Mary | B81: Taft | C81: Marketing | D81: Contract | E81: 36199 | G81: 31270 | H81: 5 | I81: =IF(OR(Table2[[#This Row],[Rating]]=4,Table2[[#This Row],[Rating]]=5), 0.05*Table2[[#This Row],[Salary]],0) -> 1563.5 | J81: =VLOOKUP(Table2[[#This Row],[Salary]],'Tax rates'!A$2:C$8, 2) + VLOOKUP(Table2[[#This Row],[Salary]],'Tax rates'!A$2:C$8, 3) * (Table2[[#This Row],[Salary]] - VLOOKUP(Table2[[#This Row],[Salary]],'Tax rates'!A$2:C$8,1)) -> 3561.9 | K81: =Table2[[#This Row],[Salary]]-Table2[[#This Row],[Taxes]] -> 27708.1 | L81: =Table2[[#This Row],[After tax salary]]+Table2[[#This Row],[Bonus]] -> 29271.6
A82: Dunn, Matthew | B82: North | C82: Environmental Compliance | D82: Full Time | E82: 36214 | F82: D | G82: 47850 | H82: 1 | I82: =IF(OR(Table2[[#This Row],[Rating]]=4,Table2[[#This Row],[Rating]]=5), 0.05*Table2[[#This Row],[Salary]],0) -> 0 | J82: =VLOOKUP(Table2[[#This Row],[Salary]],'Tax rates'!A$2:C$8, 2) + VLOOKUP(Table2[[#This Row],[Salary]],'Tax rates'!A$2:C$8, 3) * (Table2[[#This Row],[Salary]] - VLOOKUP(Table2[[#This Row],[Salary]],'Tax rates'!A$2:C$8,1)) -> 6466.5 | K82: =Table2[[#This Row],[Salary]]-Table2[[#This Row],[Taxes]] -> 41383.5 | L82: =Table2[[#This Row],[After tax salary]]+Table2[[#This Row],[Bonus]] -> 41383.5
A83: Hoffman, Brian D | B83: North | C83: Quality Assurance | D83: Contract | E83: 36214 | G83: 53310 | H83: 5 | I83: =IF(OR(Table2[[#This Row],[Rating]]=4,Table2[[#This Row],[Rating]]=5), 0.05*Table2[[#This Row],[Salary]],0) -> 2665.5 | J83: =VLOOKUP(Table2[[#This Row],[Salary]],'Tax rates'!A$2:C$8, 2) + VLOOKUP(Table2[[#This Row],[Salary]],'Tax rates'!A$2:C$8, 3) * (Table2[[#This Row],[Salary]] - VLOOKUP(Table2[[#This Row],[Salary]],'Tax rates'!A$2:C$8,1)) -> 7667.7 | K83: =Table2[[#This Row],[Salary]]-Table2[[#This Row],[Taxes]] -> 45642.3 | L83: =Table2[[#This Row],[After tax salary]]+Table2[[#This Row],[Bonus]] -> 48307.8
A84: Kirby, Michael | B84: South | C84: Account Management | D84: Half-Time | E84: 36217 | F84: R | G84: 22475 | H84: 4 | I84: =IF(OR(Table2[[#This Row],[Rating]]=4,Table2[[#This Row],[Rating]]=5), 0.05*Table2[[#This Row],[Salary]],0) -> 1123.75 | J84: =VLOOKUP(Table2[[#This Row],[Salary]],'Tax rates'!A$2:C$8, 2) + VLOOKUP(Table2[[#This Row],[Salary]],'Tax rates'!A$2:C$8, 3) * (Table2[[#This Row],[Salary]] - VLOOKUP(Table2[[#This Row],[Salary]],'Tax rates'!A$2:C$8,1)) -> 2506.5 | K84: =Table2[[#This Row],[Salary]]-Table2[[#This Row],[Taxes]] -> 19968.5 | L84: =Table2[[#This Row],[After tax salary]]+Table2[[#This Row],[Bonus]] -> 21092.25
A85: Oconnor, Kent | B85: Taft | C85: Training | D85: Half-Time | E85: 36217 | F85: DMR | G85: 15240 | H85: 1 | I85: =IF(OR(Table2[[#This Row],[Rating]]=4,Table2[[#This Row],[Rating]]=5), 0.05*Table2[[#This Row],[Salary]],0) -> 0 | J85: =VLOOKUP(Table2[[#This Row],[Salary]],'Tax rates'!A$2:C$8, 2) + VLOOKUP(Table2[[#This Row],[Salary]],'Tax rates'!A$2:C$8, 3) * (Table2[[#This Row],[Salary]] - VLOOKUP(Table2[[#This Row],[Salary]],'Tax rates'!A$2:C$8,1)) -> 1638.3 | K85: =Table2[[#This Row],[Salary]]-Table2[[#This Row],[Taxes]] -> 13601.7 | L85: =Table2[[#This Row],[After tax salary]]+Table2[[#This Row],[Bonus]] -> 13601.7
A86: Palmer, Terry | B86: South | C86: Quality Control | D86: Full Time | E86: 36243 | F86: D | G86: 77680 | H86: 3 | I86: =IF(OR(Table2[[#This Row],[Rating]]=4,Table2[[#This Row],[Rating]]=5), 0.05*Table2[[#This Row],[Salary]],0) -> 0 | J86: =VLOOKUP(Table2[[#This Row],[Salary]],'Tax rates'!A$2:C$8, 2) + VLOOKUP(Table2[[#This Row],[Salary]],'Tax rates'!A$2:C$8, 3) * (Table2[[#This Row],[Salary]] - VLOOKUP(Table2[[#This Row],[Salary]],'Tax rates'!A$2:C$8,1)) -> 13029.1 | K86: =Table2[[#This Row],[Salary]]-Table2[[#This Row],[Taxes]] -> 64650.9 | L86: =Table2[[#This Row],[After tax salary]]+Table2[[#This Row],[Bonus]] -> 64650.9
A87: Solomon, Michael | B87: North | C87: Quality Assurance | D87: Full Time | E87: 36245 | F87: DMR | G87: 58410 | H87: 5 | I87: =IF(OR(Table2[[#This Row],[Rating]]=4,Table2[[#This Row],[Rating]]=5), 0.05*Table2[[#This Row],[Salary]],0) -> 2920.5 | J87: =VLOOKUP(Table2[[#This Row],[Salary]],'Tax rates'!A$2:C$8, 2) + VLOOKUP(Table2[[#This Row],[Salary]],'Tax rates'!A$2:C$8, 3) * (Table2[[#This Row],[Salary]] - VLOOKUP(Table2[[#This Row],[Salary]],'Tax rates'!A$2:C$8,1)) -> 8789.7 | K87: =Table2[[#This Row],[Salary]]-Table2[[#This Row],[Taxes]] -> 49620.3 | L87: =Table2[[#This Row],[After tax salary]]+Table2[[#This Row],[Bonus]] -> 52540.8
A88: Foley, Peter | B88: Main | C88: Environmental Health/Safety | D88: Full Time | E88: 36249 | F88: DMR | G88: 49860 | H88: 2 | I88: =IF(OR(Table2[[#This Row],[Rating]]=4,Table2[[#This Row],[Rating]]=5), 0.05*Table2[[#This Row],[Salary]],0) -> 0 | J88: =VLOOKUP(Table2[[#This Row],[Salary]],'Tax rates'!A$2:C$8, 2) + VLOOKUP(Table2[[#This Row],[Salary]],'Tax rates'!A$2:C$8, 3) * (Table2[[#This Row],[Salary]] - VLOOKUP(Table2[[#This Row],[Salary]],'Tax rates'!A$2:C$8,1)) -> 6908.7 | K88: =Table2[[#This Row],[Salary]]-Table2[[#This Row],[Taxes]] -> 42951.3 | L88: =Table2[[#This Row],[After tax salary]]+Table2[[#This Row],[Bonus]] -> 42951.3
A89: Wiggins, Frank | B89: North | C89: Training | D89: Full Time | E89: 36260 | F89: DMR | G89: 75150 | H89: 1 | I89: =IF(OR(Table2[[#This Row],[Rating]]=4,Table2[[#This Row],[Rating]]=5), 0.05*Table2[[#This Row],[Salary]],0) -> 0 | J89: =VLOOKUP(Table2[[#This Row],[Salary]],'Tax rates'!A$2:C$8, 2) + VLOOKUP(Table2[[#This Row],[Salary]],'Tax rates'!A$2:C$8, 3) * (Table2[[#This Row],[Salary]] - VLOOKUP(Table2[[#This Row],[Salary]],'Tax rates'!A$2:C$8,1)) -> 12472.5 | K89: =Table2[[#This Row],[Salary]]-Table2[[#This Row],[Taxes]] -> 62677.5 | L89: =Table2[[#This Row],[After tax salary]]+Table2[[#This Row],[Bonus]] -> 62677.5
A90: Montgomery, Chris | B90: South | C90: Product Development | D90: Hourly | E90: 36263 | G90: 38768 | H90: 4 | I90: =IF(OR(Table2[[#This Row],[Rating]]=4,Table2[[#This Row],[Rating]]=5), 0.05*Table2[[#This Row],[Salary]],0) -> 1938.4 | J90: =VLOOKUP(Table2[[#This Row],[Salary]],'Tax rates'!A$2:C$8, 2) + VLOOKUP(Table2[[#This Row],[Salary]],'Tax rates'!A$2:C$8, 3) * (Table2[[#This Row],[Salary]] - VLOOKUP(Table2[[#This Row],[Salary]],'Tax rates'!A$2:C$8,1)) -> 4468.46 | K90: =Table2[[#This Row],[Salary]]-Table2[[#This Row],[Taxes]] -> 34299.54 | L90: =Table2[[#This Row],[After tax salary]]+Table2[[#This Row],[Bonus]] -> 36237.94
A91: Francis, Todd | B91: Main | C91: Manufacturing | D91: Half-Time | E91: 36269 | F91: R | G91: 48190 | H91: 1 | I91: =IF(OR(Table2[[#This Row],[Rating]]=4,Table2[[#This Row],[Rating]]=5), 0.05*Table2[[#This Row],[Salary]],0) -> 0 | J91: =VLOOKUP(Table2[[#This Row],[Salary]],'Tax rates'!A$2:C$8, 2) + VLOOKUP(Table2[[#This Row],[Salary]],'Tax rates'!A$2:C$8, 3) * (Table2[[#This Row],[Salary]] - VLOOKUP(Table2[[#This Row],[Salary]],'Tax rates'!A$2:C$8,1)) -> 6541.3 | K91: =Table2[[#This Row],[Salary]]-Table2[[#This Row],[Taxes]] -> 41648.7 | L91: =Table2[[#This Row],[After tax salary]]+Table2[[#This Row],[Bonus]] -> 41648.7
A92: Winters, Shaun | B92: North | C92: Creative | D92: Full Time | E92: 36269 | F92: R | G92: 61330 | H92: 1 | I92: =IF(OR(Table2[[#This Row],[Rating]]=4,Table2[[#This Row],[Rating]]=5), 0.05*Table2[[#This Row],[Salary]],0) -> 0 | J92: =VLOOKUP(Table2[[#This Row],[Salary]],'Tax rates'!A$2:C$8, 2) + VLOOKUP(Table2[[#This Row],[Salary]],'Tax rates'!A$2:C$8, 3) * (Table2[[#This Row],[Salary]] - VLOOKUP(Table2[[#This Row],[Salary]],'Tax rates'!A$2:C$8,1)) -> 9432.1 | K92: =Table2[[#This Row],[Salary]]-Table2[[#This Row],[Taxes]] -> 51897.9 | L92: =Table2[[#This Row],[After tax salary]]+Table2[[#This Row],[Bonus]] -> 51897.9
A93: Wright, Brad | B93: Main | C93: Manufacturing | D93: Full Time | E93: 36273 | F93: R | G93: 61330 | H93: 4 | I93: =IF(OR(Table2[[#This Row],[Rating]]=4,Table2[[#This Row],[Rating]]=5), 0.05*Table2[[#This Row],[Salary]],0) -> 3066.5 | J93: =VLOOKUP(Table2[[#This Row],[Salary]],'Tax rates'!A$2:C$8, 2) + VLOOKUP(Table2[[#This Row],[Salary]],'Tax rates'!A$2:C$8, 3) * (Table2[[#This Row],[Salary]] - VLOOKUP(Table2[[#This Row],[Salary]],'Tax rates'!A$2:C$8,1)) -> 9432.1 | K93: =Table2[[#This Row],[Salary]]-Table2[[#This Row],[Taxes]] -> 51897.9 | L93: =Table2[[#This Row],[After tax salary]]+Table2[[#This Row],[Bonus]] -> 54964.4
A94: Pittman, Bacardi | B94: South | C94: Manufacturing | D94: Contract | E94: 36283 | G94: 25130 | H94: 5 | I94: =IF(OR(Table2[[#This Row],[Rating]]=4,Table2[[#This Row],[Rating]]=5), 0.05*Table2[[#This Row],[Salary]],0) -> 1256.5 | J94: =VLOOKUP(Table2[[#This Row],[Salary]],'Tax rates'!A$2:C$8, 2) + VLOOKUP(Table2[[#This Row],[Salary]],'Tax rates'!A$2:C$8, 3) * (Table2[[#This Row],[Salary]] - VLOOKUP(Table2[[#This Row],[Salary]],'Tax rates'!A$2:C$8,1)) -> 2825.1 | K94: =Table2[[#This Row],[Salary]]-Table2[[#This Row],[Taxes]] -> 22304.9 | L94: =Table2[[#This Row],[After tax salary]]+Table2[[#This Row],[Bonus]] -> 23561.4
A95: Aguilar, Kevin | B95: West | C95: Quality Assurance | D95: Full Time | E95: 36290 | F95: R | G95: 39000 | H95: 3 | I95: =IF(OR(Table2[[#This Row],[Rating]]=4,Table2[[#This Row],[Rating]]=5), 0.05*Table2[[#This Row],[Salary]],0) -> 0 | J95: =VLOOKUP(Table2[[#This Row],[Salary]],'Tax rates'!A$2:C$8, 2) + VLOOKUP(Table2[[#This Row],[Salary]],'Tax rates'!A$2:C$8, 3) * (Table2[[#This Row],[Salary]] - VLOOKUP(Table2[[#This Row],[Salary]],'Tax rates'!A$2:C$8,1)) -> 4519.5 | K95: =Table2[[#This Row],[Salary]]-Table2[[#This Row],[Taxes]] -> 34480.5 | L95: =Table2[[#This Row],[After tax salary]]+Table2[[#This Row],[Bonus]] -> 34480.5
A96: Soto, Christopher | B96: Main | C96: Account Management | D96: Contract | E96: 36297 | G96: 57990 | H96: 5 | I96: =IF(OR(Table2[[#This Row],[Rating]]=4,Table2[[#This Row],[Rating]]=5), 0.05*Table2[[#This Row],[Salary]],0) -> 2899.5 | J96: =VLOOKUP(Table2[[#This Row],[Salary]],'Tax rates'!A$2:C$8, 2) + VLOOKUP(Table2[[#This Row],[Salary]],'Tax rates'!A$2:C$8, 3) * (Table2[[#This Row],[Salary]] - VLOOKUP(Table2[[#This Row],[Salary]],'Tax rates'!A$2:C$8,1)) -> 8697.3 | K96: =Table2[[#This Row],[Salary]]-Table2[[#This Row],[Taxes]] -> 49292.7 | L96: =Table2[[#This Row],[After tax salary]]+Table2[[#This Row],[Bonus]] -> 52192.2
A97: Love, Danny | B97: Watson | C97: Marketing | D97: Full Time | E97: 36297 | F97: DMR | G97: 46030 | H97: 2 | I97: =IF(OR(Table2[[#This Row],[Rating]]=4,Table2[[#This Row],[Rating]]=5), 0.05*Table2[[#This Row],[Salary]],0) -> 0 | J97: =VLOOKUP(Table2[[#This Row],[Salary]],'Tax rates'!A$2:C$8, 2) + VLOOKUP(Table2[[#This Row],[Salary]],'Tax rates'!A$2:C$8, 3) * (Table2[[#This Row],[Salary]] - VLOOKUP(Table2[[#This Row],[Salary]],'Tax rates'!A$2:C$8,1)) -> 6066.1 | K97: =Table2[[#This Row],[Salary]]-Table2[[#This Row],[Taxes]] -> 39963.9 | L97: =Table2[[#This Row],[After tax salary]]+Table2[[#This Row],[Bonus]] -> 39963.9
A98: Hurst, Thomas | B98: Main | C98: Manufacturing | D98: Hourly | E98: 36305 | G98: 9424 | H98: 4 | I98: =IF(OR(Table2[[#This Row],[Rating]]=4,Table2[[#This Row],[Rating]]=5), 0.05*Table2[[#This Row],[Salary]],0) -> 471.2 | J98: =VLOOKUP(Table2[[#This Row],[Salary]],'Tax rates'!A$2:C$8, 2) + VLOOKUP(Table2[[#This Row],[Salary]],'Tax rates'!A$2:C$8, 3) * (Table2[[#This Row],[Salary]] - VLOOKUP(Table2[[#This Row],[Salary]],'Tax rates'!A$2:C$8,1)) -> 942.4 | K98: =Table2[[#This Row],[Salary]]-Table2[[#This Row],[Taxes]] -> 8481.6 | L98: =Table2[[#This Row],[After tax salary]]+Table2[[#This Row],[Bonus]] -> 8952.8
A99: Gaines, Sheela | B99: North | C99: Quality Assurance | D99: Full Time | E99: 36312 | F99: DMR | G99: 69200 | H99: 4 | I99: =IF(OR(Table2[[#This Row],[Rating]]=4,Table2[[#This Row],[Rating]]=5), 0.05*Table2[[#This Row],[Salary]],0) -> 3460 | J99: =VLOOKUP(Table2[[#This Row],[Salary]],'Tax rates'!A$2:C$8, 2) + VLOOKUP(Table2[[#This Row],[Salary]],'Tax rates'!A$2:C$8, 3) * (Table2[[#This Row],[Salary]] - VLOOKUP(Table2[[#This Row],[Salary]],'Tax rates'!A$2:C$8,1)) -> 11163.5 | K99: =Table2[[#This Row],[Salary]]-Table2[[#This Row],[Taxes]] -> 58036.5 | L99: =Table2[[#This Row],[After tax salary]]+Table2[[#This Row],[Bonus]] -> 61496.5
A100: Sullivan, Robert | B100: North | C100: Manufacturing | D100: Full Time | E100: 36318 | F100: R | G100: 68750 | H100: 1 | I100: =IF(OR(Table2[[#This Row],[Rating]]=4,Table2[[#This Row],[Rating]]=5), 0.05*Table2[[#This Row],[Salary]],0) -> 0 | J100: =VLOOKUP(Table2[[#This Row],[Salary]],'Tax rates'!A$2:C$8, 2) + VLOOKUP(Table2[[#This Row],[Salary]],'Tax rates'!A$2:C$8, 3) * (Table2[[#This Row],[Salary]] - VLOOKUP(Table2[[#This Row],[Salary]],'Tax rates'!A$2:C$8,1)) -> 11064.5 | K100: =Table2[[#This Row],[Salary]]-Table2[[#This Row],[Taxes]] -> 57685.5 | L100: =Table2[[#This Row],[After tax salary]]+Table2[[#This Row],[Bonus]] -> 57685.5
...

Sheet Tax rates
A1: Salary greater or equal than | B1: Fixed amount | C1: Percentage | D1: Of the difference with
A2: 0 | B2: 0 | C2: 0.1 | D2: 0
A3: 9525 | B3: 952.5 | C3: 0.12 | D3: =A3 -> 9525
A4: 38700 | B4: 4453.5 | C4: 0.22 | D4: =A4 -> 38700
A5: 82500 | B5: 14089.5 | C5: 0.24 | D5: =A5 -> 82500
A6: 157500 | B6: 32089.5 | C6: 0.32 | D6: =A6 -> 157500
A7: 200000 | B7: 45689.5 | C7: 0.35 | D7: =A7 -> 200000
A8: 500000 | B8: 150689.5 | C8: 0.37 | D8: =A8 -> 500000

Sheet With data validation
A1: Names | B1: Building | C1: Department | D1: Status | E1: Hiring date | F1: Benefits | G1: Salary | H1: Rating | I1: Bonus | J1: Taxes | K1: After tax salary
A2: Disha | B2: Watson | C2: IT | L2: <-insert data here to see the data validation
A3: Burnett, Kevin | B3: Main | C3: Account Management | D3: Full Time | E3: 40624 | F3: D | G3: 86500 | H3: 1 | I3: =IF(OR(Table24[[#This Row],[Rating]]=4,Table24[[#This Row],[Rating]]=5), 0.05*Table24[[#This Row],[Salary]],0) -> 0 | J3: =VLOOKUP(Table24[[#This Row],[Salary]],'Tax rates'!A$2:C$8, 2) + VLOOKUP(Table24[[#This Row],[Salary]],'Tax rates'!A$2:C$8, 3) * (Table24[[#This Row],[Salary]] - VLOOKUP(Table24[[#This Row],[Salary]],'Tax rates'!A$2:C$8,1)) -> 15049.5 | K3: =Table24[[#This Row],[Salary]]-Table24[[#This Row],[Taxes]] -> 71450.5
A4: Herrera, Shawn | B4: Main | C4: Account Management | D4: Full Time | E4: 40831 | F4: M | G4: 79400 | H4: 4 | I4: =IF(OR(Table24[[#This Row],[Rating]]=4,Table24[[#This Row],[Rating]]=5), 0.05*Table24[[#This Row],[Salary]],0) -> 3970 | J4: =VLOOKUP(Table24[[#This Row],[Salary]],'Tax rates'!A$2:C$8, 2) + VLOOKUP(Table24[[#This Row],[Salary]],'Tax rates'!A$2:C$8, 3) * (Table24[[#This Row],[Salary]] - VLOOKUP(Table24[[#This Row],[Salary]],'Tax rates'!A$2:C$8,1)) -> 13407.5 | K4: =Table24[[#This Row],[Salary]]-Table24[[#This Row],[Taxes]] -> 65992.5
A5: Roman, Teri | B5: Main | C5: Account Management | D5: Contract | E5: 40707 | G5: 79380 | H5: 1 | I5: =IF(OR(Table24[[#This Row],[Rating]]=4,Table24[[#This Row],[Rating]]=5), 0.05*Table24[[#This Row],[Salary]],0) -> 0 | J5: =VLOOKUP(Table24[[#This Row],[Salary]],'Tax rates'!A$2:C$8, 2) + VLOOKUP(Table24[[#This Row],[Salary]],'Tax rates'!A$2:C$8, 3) * (Table24[[#This Row],[Salary]] - VLOOKUP(Table24[[#This Row],[Salary]],'Tax rates'!A$2:C$8,1)) -> 13403.1 | K5: =Table24[[#This Row],[Salary]]-Table24[[#This Row],[Taxes]] -> 65976.9
A6: William, William | B6: Main | C6: Account Management | D6: Full Time | E6: 40765 | F6: M | G6: 77740 | H6: 1 | I6: =IF(OR(Table24[[#This Row],[Rating]]=4,Table24[[#This Row],[Rating]]=5), 0.05*Table24[[#This Row],[Salary]],0) -> 0 | J6: =VLOOKUP(Table24[[#This Row],[Salary]],'Tax rates'!A$2:C$8, 2) + VLOOKUP(Table24[[#This Row],[Salary]],'Tax rates'!A$2:C$8, 3) * (Table24[[#This Row],[Salary]] - VLOOKUP(Table24[[#This Row],[Salary]],'Tax rates'!A$2:C$8,1)) -> 13042.3 | K6: =Table24[[#This Row],[Salary]]-Table24[[#This Row],[Taxes]] -> 64697.7
A7: Lawson, Erin | B7: Main | C7: Account Management | D7: Full Time | E7: 39282 | F7: M | G7: 69420 | H7: 2 | I7: =IF(OR(Table24[[#This Row],[Rating]]=4,Table24[[#This Row],[Rating]]=5), 0.05*Table24[[#This Row],[Salary]],0) -> 0 | J7: =VLOOKUP(Table24[[#This Row],[Salary]],'Tax rates'!A$2:C$8, 2) + VLOOKUP(Table24[[#This Row],[Salary]],'Tax rates'!A$2:C$8, 3) * (Table24[[#This Row],[Salary]] - VLOOKUP(Table24[[#This Row],[Salary]],'Tax rates'!A$2:C$8,1)) -> 11211.9 | K7: =Table24[[#This Row],[Salary]]-Table24[[#This Row],[Taxes]] -> 58208.1
A8: Vargas, Bryant | B8: Main | C8: Account Management | D8: Full Time | E8: 36393 | F8: R | G8: 65910 | H8: 5 | I8: =IF(OR(Table24[[#This Row],[Rating]]=4,Table24[[#This Row],[Rating]]=5), 0.05*Table24[[#This Row],[Salary]],0) -> 3295.5 | J8: =VLOOKUP(Table24[[#This Row],[Salary]],'Tax rates'!A$2:C$8, 2) + VLOOKUP(Table24[[#This Row],[Salary]],'Tax rates'!A$2:C$8, 3) * (Table24[[#This Row],[Salary]] - VLOOKUP(Table24[[#This Row],[Salary]],'Tax rates'!A$2:C$8,1)) -> 10439.7 | K8: =Table24[[#This Row],[Salary]]-Table24[[#This Row],[Taxes]] -> 55470.3
A9: Reid, Elizabeth | B9: Main | C9: Account Management | D9: Full Time | E9: 39047 | F9: R | G9: 65880 | H9: 5 | I9: =IF(OR(Table24[[#This Row],[Rating]]=4,Table24[[#This Row],[Rating]]=5), 0.05*Table24[[#This Row],[Salary]],0) -> 3294 | J9: =VLOOKUP(Table24[[#This Row],[Salary]],'Tax rates'!A$2:C$8, 2) + VLOOKUP(Table24[[#This Row],[Salary]],'Tax rates'!A$2:C$8, 3) * (Table24[[#This Row],[Salary]] - VLOOKUP(Table24[[#This Row],[Salary]],'Tax rates'!A$2:C$8,1)) -> 10433.1 | K9: =Table24[[#This Row],[Salary]]-Table24[[#This Row],[Taxes]] -> 55446.9
A10: Austin, William | B10: Main | C10: Account Management | D10: Full Time | E10: 39335 | F10: DMR | G10: 62688 | H10: 2 | I10: =IF(OR(Table24[[#This Row],[Rating]]=4,Table24[[#This Row],[Rating]]=5), 0.05*Table24[[#This Row],[Salary]],0) -> 0 | J10: =VLOOKUP(Table24[[#This Row],[Salary]],'Tax rates'!A$2:C$8, 2) + VLOOKUP(Table24[[#This Row],[Salary]],'Tax rates'!A$2:C$8, 3) * (Table24[[#This Row],[Salary]] - VLOOKUP(Table24[[#This Row],[Salary]],'Tax rates'!A$2:C$8,1)) -> 9730.86 | K10: =Table24[[#This Row],[Salary]]-Table24[[#This Row],[Taxes]] -> 52957.14
A11: Hayes, Edward | B11: Main | C11: Account Management | D11: Full Time | E11: 36536 | F11: DMR | G11: 62400 | H11: 4 | I11: =IF(OR(Table24[[#This Row],[Rating]]=4,Table24[[#This Row],[Rating]]=5), 0.05*Table24[[#This Row],[Salary]],0) -> 3120 | J11: =VLOOKUP(Table24[[#This Row],[Salary]],'Tax rates'!A$2:C$8, 2) + VLOOKUP(Table24[[#This Row],[Salary]],'Tax rates'!A$2:C$8, 3) * (Table24[[#This Row],[Salary]] - VLOOKUP(Table24[[#This Row],[Salary]],'Tax rates'!A$2:C$8,1)) -> 9667.5 | K11: =Table24[[#This Row],[Salary]]-Table24[[#This Row],[Taxes]] -> 52732.5
A12: Vasquez, Michael | B12: Main | C12: Account Management | D12: Contract | E12: 37404 | G12: 60070 | H12: 3 | I12: =IF(OR(Table24[[#This Row],[Rating]]=4,Table24[[#This Row],[Rating]]=5), 0.05*Table24[[#This Row],[Salary]],0) -> 0 | J12: =VLOOKUP(Table24[[#This Row],[Salary]],'Tax rates'!A$2:C$8, 2) + VLOOKUP(Table24[[#This Row],[Salary]],'Tax rates'!A$2:C$8, 3) * (Table24[[#This Row],[Salary]] - VLOOKUP(Table24[[#This Row],[Salary]],'Tax rates'!A$2:C$8,1)) -> 9154.9 | K12: =Table24[[#This Row],[Salary]]-Table24[[#This Row],[Taxes]] -> 50915.1
A13: Glass, John | B13: Main | C13: Account Management | D13: Contract | E13: 39809 | G13: 58650 | H13: 4 | I13: =IF(OR(Table24[[#This Row],[Rating]]=4,Table24[[#This Row],[Rating]]=5), 0.05*Table24[[#This Row],[Salary]],0) -> 2932.5 | J13: =VLOOKUP(Table24[[#This Row],[Salary]],'Tax rates'!A$2:C$8, 2) + VLOOKUP(Table24[[#This Row],[Salary]],'Tax rates'!A$2:C$8, 3) * (Table24[[#This Row],[Salary]] - VLOOKUP(Table24[[#This Row],[Salary]],'Tax rates'!A$2:C$8,1)) -> 8842.5 | K13: =Table24[[#This Row],[Salary]]-Table24[[#This Row],[Taxes]] -> 49807.5
A14: Soto, Christopher | B14: Main | C14: Account Management | D14: Contract | E14: 36297 | G14: 57990 | H14: 5 | I14: =IF(OR(Table24[[#This Row],[Rating]]=4,Table24[[#This Row],[Rating]]=5), 0.05*Table24[[#This Row],[Salary]],0) -> 2899.5 | J14: =VLOOKUP(Table24[[#This Row],[Salary]],'Tax rates'!A$2:C$8, 2) + VLOOKUP(Table24[[#This Row],[Salary]],'Tax rates'!A$2:C$8, 3) * (Table24[[#This Row],[Salary]] - VLOOKUP(Table24[[#This Row],[Salary]],'Tax rates'!A$2:C$8,1)) -> 8697.3 | K14: =Table24[[#This Row],[Salary]]-Table24[[#This Row],[Taxes]] -> 49292.7
A15: Shaw, Pat | B15: Main | C15: Account Management | D15: Contract | E15: 39592 | G15: 56650 | H15: 1 | I15: =IF(OR(Table24[[#This Row],[Rating]]=4,Table24[[#This Row],[Rating]]=5), 0.05*Table24[[#This Row],[Salary]],0) -> 0 | J15: =VLOOKUP(Table24[[#This Row],[Salary]],'Tax rates'!A$2:C$8, 2) + VLOOKUP(Table24[[#This Row],[Salary]],'Tax rates'!A$2:C$8, 3) * (Table24[[#This Row],[Salary]] - VLOOKUP(Table24[[#This Row],[Salary]],'Tax rates'!A$2:C$8,1)) -> 8402.5 | K15: =Table24[[#This Row],[Salary]]-Table24[[#This Row],[Taxes]] -> 48247.5
A16: Moses, Mark | B16: Main | C16: Account Management | D16: Full Time | E16: 36088 | F16: M | G16: 54580 | H16: 4 | I16: =IF(OR(Table24[[#This Row],[Rating]]=4,Table24[[#This Row],[Rating]]=5), 0.05*Table24[[#This Row],[Salary]],0) -> 2729 | J16: =VLOOKUP(Table24[[#This Row],[Salary]],'Tax rates'!A$2:C$8, 2) + VLOOKUP(Table24[[#This Row],[Salary]],'Tax rates'!A$2:C$8, 3) * (Table24[[#This Row],[Salary]] - VLOOKUP(Table24[[#This Row],[Salary]],'Tax rates'!A$2:C$8,1)) -> 7947.1 | K16: =Table24[[#This Row],[Salary]]-Table24[[#This Row],[Taxes]] -> 46632.9
A17: Frank, William | B17: Main | C17: Account Management | D17: Full Time | E17: 40815 | F17: DM | G17: 54500 | H17: 5 | I17: =IF(OR(Table24[[#This Row],[Rating]]=4,Table24[[#This Row],[Rating]]=5), 0.05*Table24[[#This Row],[Salary]],0) -> 2725 | J17: =VLOOKUP(Table24[[#This Row],[Salary]],'Tax rates'!A$2:C$8, 2) + VLOOKUP(Table24[[#This Row],[Salary]],'Tax rates'!A$2:C$8, 3) * (Table24[[#This Row],[Salary]] - VLOOKUP(Table24[[#This Row],[Salary]],'Tax rates'!A$2:C$8,1)) -> 7929.5 | K17: =Table24[[#This Row],[Salary]]-Table24[[#This Row],[Taxes]] -> 46570.5
A18: Jenkins, Scott | B18: Main | C18: Account Management | D18: Full Time | E18: 40137 | F18: DMR | G18: 54190 | H18: 4 | I18: =IF(OR(Table24[[#This Row],[Rating]]=4,Table24[[#This Row],[Rating]]=5), 0.05*Table24[[#This Row],[Salary]],0) -> 2709.5 | J18: =VLOOKUP(Table24[[#This Row],[Salary]],'Tax rates'!A$2:C$8, 2) + VLOOKUP(Table24[[#This Row],[Salary]],'Tax rates'!A$2:C$8, 3) * (Table24[[#This Row],[Salary]] - VLOOKUP(Table24[[#This Row],[Salary]],'Tax rates'!A$2:C$8,1)) -> 7861.3 | K18: =Table24[[#This Row],[Salary]]-Table24[[#This Row],[Taxes]] -> 46328.7
A19: Mann, Lowell | B19: Main | C19: Account Management | D19: Contract | E19: 40820 | G19: 52750 | H19: 1 | I19: =IF(OR(Table24[[#This Row],[Rating]]=4,Table24[[#This Row],[Rating]]=5), 0.05*Table24[[#This Row],[Salary]],0) -> 0 | J19: =VLOOKUP(Table24[[#This Row],[Salary]],'Tax rates'!A$2:C$8, 2) + VLOOKUP(Table24[[#This Row],[Salary]],'Tax rates'!A$2:C$8, 3) * (Table24[[#This Row],[Salary]] - VLOOKUP(Table24[[#This Row],[Salary]],'Tax rates'!A$2:C$8,1)) -> 7544.5 | K19: =Table24[[#This Row],[Salary]]-Table24[[#This Row],[Taxes]] -> 45205.5
A20: Serrano, Al | B20: Main | C20: Account Management | D20: Full Time | E20: 36673 | F20: D | G20: 48330 | H20: 1 | I20: =IF(OR(Table24[[#This Row],[Rating]]=4,Table24[[#This Row],[Rating]]=5), 0.05*Table24[[#This Row],[Salary]],0) -> 0 | J20: =VLOOKUP(Table24[[#This Row],[Salary]],'Tax rates'!A$2:C$8, 2) + VLOOKUP(Table24[[#This Row],[Salary]],'Tax rates'!A$2:C$8, 3) * (Table24[[#This Row],[Salary]] - VLOOKUP(Table24[[#This Row],[Salary]],'Tax rates'!A$2:C$8,1)) -> 6572.1 | K20: =Table24[[#This Row],[Salary]]-Table24[[#This Row],[Taxes]] -> 41757.9
A21: Ward, Williams | B21: Main | C21: Account Management | D21: Full Time | E21: 39673 | F21: DMR | G21: 48080 | H21: 2 | I21: =IF(OR(Table24[[#This Row],[Rating]]=4,Table24[[#This Row],[Rating]]=5), 0.05*Table24[[#This Row],[Salary]],0) -> 0 | J21: =VLOOKUP(Table24[[#This Row],[Salary]],'Tax rates'!A$2:C$8, 2) + VLOOKUP(Table24[[#This Row],[Salary]],'Tax rates'!A$2:C$8, 3) * (Table24[[#This Row],[Salary]] - VLOOKUP(Table24[[#This Row],[Salary]],'Tax rates'!A$2:C$8,1)) -> 6517.1 | K21: =Table24[[#This Row],[Salary]]-Table24[[#This Row],[Taxes]] -> 41562.9
A22: Bean, Deborah | B22: Main | C22: Account Management | D22: Full Time | E22: 40332 | F22: DMR | G22: 47340 | H22: 2 | I22: =IF(OR(Table24[[#This Row],[Rating]]=4,Table24[[#This Row],[Rating]]=5), 0.05*Table24[[#This Row],[Salary]],0) -> 0 | J22: =VLOOKUP(Table24[[#This Row],[Salary]],'Tax rates'!A$2:C$8, 2) + VLOOKUP(Table24[[#This Row],[Salary]],'Tax rates'!A$2:C$8, 3) * (Table24[[#This Row],[Salary]] - VLOOKUP(Table24[[#This Row],[Salary]],'Tax rates'!A$2:C$8,1)) -> 6354.3 | K22: =Table24[[#This Row],[Salary]]-Table24[[#This Row],[Taxes]] -> 40985.7
A23: Carter, Allan | B23: Main | C23: Account Management | D23: Full Time | E23: 36195 | F23: M | G23: 46360 | H23: 5 | I23: =IF(OR(Table24[[#This Row],[Rating]]=4,Table24[[#This Row],[Rating]]=5), 0.05*Table24[[#This Row],[Salary]],0) -> 2318 | J23: =VLOOKUP(Table24[[#This Row],[Salary]],'Tax rates'!A$2:C$8, 2) + VLOOKUP(Table24[[#This Row],[Salary]],'Tax rates'!A$2:C$8, 3) * (Table24[[#This Row],[Salary]] - VLOOKUP(Table24[[#This Row],[Salary]],'Tax rates'!A$2:C$8,1)) -> 6138.7 | K23: =Table24[[#This Row],[Salary]]-Table24[[#This Row],[Taxes]] -> 40221.3
A24: Solis, Daniel | B24: Main | C24: Account Management | D24: Contract | E24: 41254 | G24: 44720 | H24: 2 | I24: =IF(OR(Table24[[#This Row],[Rating]]=4,Table24[[#This Row],[Rating]]=5), 0.05*Table24[[#This Row],[Salary]],0) -> 0 | J24: =VLOOKUP(Table24[[#This Row],[Salary]],'Tax rates'!A$2:C$8, 2) + VLOOKUP(Table24[[#This Row],[Salary]],'Tax rates'!A$2:C$8, 3) * (Table24[[#This Row],[Salary]] - VLOOKUP(Table24[[#This Row],[Salary]],'Tax rates'!A$2:C$8,1)) -> 5777.9 | K24: =Table24[[#This Row],[Salary]]-Table24[[#This Row],[Taxes]] -> 38942.1
A25: Wiley, Gustavo | B25: Main | C25: Account Management | D25: Contract | E25: 40404 | G25: 39550 | H25: 5 | I25: =IF(OR(Table24[[#This Row],[Rating]]=4,Table24[[#This Row],[Rating]]=5), 0.05*Table24[[#This Row],[Salary]],0) -> 1977.5 | J25: =VLOOKUP(Table24[[#This Row],[Salary]],'Tax rates'!A$2:C$8, 2) + VLOOKUP(Table24[[#This Row],[Salary]],'Tax rates'!A$2:C$8, 3) * (Table24[[#This Row],[Salary]] - VLOOKUP(Table24[[#This Row],[Salary]],'Tax rates'!A$2:C$8,1)) -> 4640.5 | K25: =Table24[[#This Row],[Salary]]-Table24[[#This Row],[Taxes]] -> 34909.5
A26: Preston, Chris | B26: Main | C26: Account Management | D26: Full Time | E26: 35990 | F26: D | G26: 36890 | H26: 1 | I26: =IF(OR(Table24[[#This Row],[Rating]]=4,Table24[[#This Row],[Rating]]=5), 0.05*Table24[[#This Row],[Salary]],0) -> 0 | J26: =VLOOKUP(Table24[[#This Row],[Salary]],'Tax rates'!A$2:C$8, 2) + VLOOKUP(Table24[[#This Row],[Salary]],'Tax rates'!A$2:C$8, 3) * (Table24[[#This Row],[Salary]] - VLOOKUP(Table24[[#This Row],[Salary]],'Tax rates'!A$2:C$8,1)) -> 4236.3 | K26: =Table24[[#This Row],[Salary]]-Table24[[#This Row],[Taxes]] -> 32653.7
A27: Howell, Douglas | B27: Main | C27: Account Management | D27: Hourly | E27: 36380 | G27: 36052 | H27: 5 | I27: =IF(OR(Table24[[#This Row],[Rating]]=4,Table24[[#This Row],[Rating]]=5), 0.05*Table24[[#This Row],[Salary]],0) -> 1802.6 | J27: =VLOOKUP(Table24[[#This Row],[Salary]],'Tax rates'!A$2:C$8, 2) + VLOOKUP(Table24[[#This Row],[Salary]],'Tax rates'!A$2:C$8, 3) * (Table24[[#This Row],[Salary]] - VLOOKUP(Table24[[#This Row],[Salary]],'Tax rates'!A$2:C$8,1)) -> 4135.74 | K27: =Table24[[#This Row],[Salary]]-Table24[[#This Row],[Taxes]] -> 31916.26
A28: Gutierrez, Regina | B28: Main | C28: Account Management | D28: Contract | E28: 39109 | G28: 33120 | H28: 2 | I28: =IF(OR(Table24[[#This Row],[Rating]]=4,Table24[[#This Row],[Rating]]=5), 0.05*Table24[[#This Row],[Salary]],0) -> 0 | J28: =VLOOKUP(Table24[[#This Row],[Salary]],'Tax rates'!A$2:C$8, 2) + VLOOKUP(Table24[[#This Row],[Salary]],'Tax rates'!A$2:C$8, 3) * (Table24[[#This Row],[Salary]] - VLOOKUP(Table24[[#This Row],[Salary]],'Tax rates'!A$2:C$8,1)) -> 3783.9 | K28: =Table24[[#This Row],[Salary]]-Table24[[#This Row],[Taxes]] -> 29336.1
A29: Wilson, Jessica | B29: Main | C29: Account Management | D29: Full Time | E29: 37138 | F29: DMR | G29: 29130 | H29: 1 | I29: =IF(OR(Table24[[#This Row],[Rating]]=4,Table24[[#This Row],[Rating]]=5), 0.05*Table24[[#This Row],[Salary]],0) -> 0 | J29: =VLOOKUP(Table24[[#This Row],[Salary]],'Tax rates'!A$2:C$8, 2) + VLOOKUP(Table24[[#This Row],[Salary]],'Tax rates'!A$2:C$8, 3) * (Table24[[#This Row],[Salary]] - VLOOKUP(Table24[[#This Row],[Salary]],'Tax rates'!A$2:C$8,1)) -> 3305.1 | K29: =Table24[[#This Row],[Salary]]-Table24[[#This Row],[Taxes]] -> 25824.9
A30: Cabe, Max | B30: Main | C30: Account Management | D30: Half-Time | E30: 40166 | F30: D | G30: 25245 | H30: 5 | I30: =IF(OR(Table24[[#This Row],[Rating]]=4,Table24[[#This Row],[Rating]]=5), 0.05*Table24[[#This Row],[Salary]],0) -> 1262.25 | J30: =VLOOKUP(Table24[[#This Row],[Salary]],'Tax rates'!A$2:C$8, 2) + VLOOKUP(Table24[[#This Row],[Salary]],'Tax rates'!A$2:C$8, 3) * (Table24[[#This Row],[Salary]] - VLOOKUP(Table24[[#This Row],[Salary]],'Tax rates'!A$2:C$8,1)) -> 2838.9 | K30: =Table24[[#This Row],[Salary]]-Table24[[#This Row],[Taxes]] -> 22406.1
A31: Lynch, Scott | B31: Main | C31: Account Management | D31: Full Time | E31: 40666 | F31: DMR | G31: 24090 | H31: 4 | I31: =IF(OR(Table24[[#This Row],[Rating]]=4,Table24[[#This Row],[Rating]]=5), 0.05*Table24[[#This Row],[Salary]],0) -> 1204.5 | J31: =VLOOKUP(Table24[[#This Row],[Salary]],'Tax rates'!A$2:C$8, 2) + VLOOKUP(Table24[[#This Row],[Salary]],'Tax rates'!A$2:C$8, 3) * (Table24[[#This Row],[Salary]] - VLOOKUP(Table24[[#This Row],[Salary]],'Tax rates'!A$2:C$8,1)) -> 2700.3 | K31: =Table24[[#This Row],[Salary]]-Table24[[#This Row],[Taxes]] -> 21389.7
A32: Ayala, Polly | B32: Main | C32: Account Management | D32: Full Time | E32: 39174 | F32: DMR | G32: 23320 | H32: 4 | I32: =IF(OR(Table24[[#This Row],[Rating]]=4,Table24[[#This Row],[Rating]]=5), 0.05*Table24[[#This Row],[Salary]],0) -> 1166 | J32: =VLOOKUP(Table24[[#This Row],[Salary]],'Tax rates'!A$2:C$8, 2) + VLOOKUP(Table24[[#This Row],[Salary]],'Tax rates'!A$2:C$8, 3) * (Table24[[#This Row],[Salary]] - VLOOKUP(Table24[[#This Row],[Salary]],'Tax rates'!A$2:C$8,1)) -> 2607.9 | K32: =Table24[[#This Row],[Salary]]-Table24[[#This Row],[Taxes]] -> 20712.1
A33: Curry, Hunyen | B33: Main | C33: Account Management | D33: Half-Time | E33: 37249 | F33: D | G33: 12545 | H33: 4 | I33: =IF(OR(Table24[[#This Row],[Rating]]=4,Table24[[#This Row],[Rating]]=5), 0.05*Table24[[#This Row],[Salary]],0) -> 627.25 | J33: =VLOOKUP(Table24[[#This Row],[Salary]],'Tax rates'!A$2:C$8, 2) + VLOOKUP(Table24[[#This Row],[Salary]],'Tax rates'!A$2:C$8, 3) * (Table24[[#This Row],[Salary]] - VLOOKUP(Table24[[#This Row],[Salary]],'Tax rates'!A$2:C$8,1)) -> 1314.9 | K33: =Table24[[#This Row],[Salary]]-Table24[[#This Row],[Taxes]] -> 11230.1
A34: Allison, Timothy | B34: Main | C34: Creative | D34: Full Time | E34: 40918 | F34: M | G34: 82500 | H34: 5 | I34: =IF(OR(Table24[[#This Row],[Rating]]=4,Table24[[#This Row],[Rating]]=5), 0.05*Table24[[#This Row],[Salary]],0) -> 4125 | J34: =VLOOKUP(Table24[[#This Row],[Salary]],'Tax rates'!A$2:C$8, 2) + VLOOKUP(Table24[[#This Row],[Salary]],'Tax rates'!A$2:C$8, 3) * (Table24[[#This Row],[Salary]] - VLOOKUP(Table24[[#This Row],[Salary]],'Tax rates'!A$2:C$8,1)) -> 14089.5 | K34: =Table24[[#This Row],[Salary]]-Table24[[#This Row],[Taxes]] -> 68410.5
A35: Figueroa, Leonard | B35: Main | C35: Creative | D35: Contract | E35: 39024 | G35: 76020 | H35: 1 | I35: =IF(OR(Table24[[#This Row],[Rating]]=4,Table24[[#This Row],[Rating]]=5), 0.05*Table24[[#This Row],[Salary]],0) -> 0 | J35: =VLOOKUP(Table24[[#This Row],[Salary]],'Tax rates'!A$2:C$8, 2) + VLOOKUP(Table24[[#This Row],[Salary]],'Tax rates'!A$2:C$8, 3) * (Table24[[#This Row],[Salary]] - VLOOKUP(Table24[[#This Row],[Salary]],'Tax rates'!A$2:C$8,1)) -> 12663.9 | K35: =Table24[[#This Row],[Salary]]-Table24[[#This Row],[Taxes]] -> 63356.1
A36: Roberson, Eileen | B36: Main | C36: Creative | D36: Contract | E36: 35959 | G36: 64470 | H36: 3 | I36: =IF(OR(Table24[[#This Row],[Rating]]=4,Table24[[#This Row],[Rating]]=5), 0.05*Table24[[#This Row],[Salary]],0) -> 0 | J36: =VLOOKUP(Table24[[#This Row],[Salary]],'Tax rates'!A$2:C$8, 2) + VLOOKUP(Table24[[#This Row],[Salary]],'Tax rates'!A$2:C$8, 3) * (Table24[[#This Row],[Salary]] - VLOOKUP(Table24[[#This Row],[Salary]],'Tax rates'!A$2:C$8,1)) -> 10122.9 | K36: =Table24[[#This Row],[Salary]]-Table24[[#This Row],[Taxes]] -> 54347.1
A37: Molina, Michael | B37: Main | C37: Creative | D37: Full Time | E37: 37113 | F37: M | G37: 61150 | H37: 4 | I37: =IF(OR(Table24[[#This Row],[Rating]]=4,Table24[[#This Row],[Rating]]=5), 0.05*Table24[[#This Row],[Salary]],0) -> 3057.5 | J37: =VLOOKUP(Table24[[#This Row],[Salary]],'Tax rates'!A$2:C$8, 2) + VLOOKUP(Table24[[#This Row],[Salary]],'Tax rates'!A$2:C$8, 3) * (Table24[[#This Row],[Salary]] - VLOOKUP(Table24[[#This Row],[Salary]],'Tax rates'!A$2:C$8,1)) -> 9392.5 | K37: =Table24[[#This Row],[Salary]]-Table24[[#This Row],[Taxes]] -> 51757.5
A38: McDowell, Scott | B38: Main | C38: Creative | D38: Full Time | E38: 36077 | F38: R | G38: 50110 | H38: 1 | I38: =IF(OR(Table24[[#This Row],[Rating]]=4,Table24[[#This Row],[Rating]]=5), 0.05*Table24[[#This Row],[Salary]],0) -> 0 | J38: =VLOOKUP(Table24[[#This Row],[Salary]],'Tax rates'!A$2:C$8, 2) + VLOOKUP(Table24[[#This Row],[Salary]],'Tax rates'!A$2:C$8, 3) * (Table24[[#This Row],[Salary]] - VLOOKUP(Table24[[#This Row],[Salary]],'Tax rates'!A$2:C$8,1)) -> 6963.7 | K38: =Table24[[#This Row],[Salary]]-Table24[[#This Row],[Taxes]] -> 43146.3
A39: Silva, Stephen | B39: Main | C39: Creative | D39: Half-Time | E39: 36357 | F39: D | G39: 42905 | H39: 1 | I39: =IF(OR(Table24[[#This Row],[Rating]]=4,Table24[[#This Row],[Rating]]=5), 0.05*Table24[[#This Row],[Salary]],0) -> 0 | J39: =VLOOKUP(Table24[[#This Row],[Salary]],'Tax rates'!A$2:C$8, 2) + VLOOKUP(Table24[[#This Row],[Salary]],'Tax rates'!A$2:C$8, 3) * (Table24[[#This Row],[Salary]] - VLOOKUP(Table24[[#This Row],[Salary]],'Tax rates'!A$2:C$8,1)) -> 5378.6 | K39: =Table24[[#This Row],[Salary]]-Table24[[#This Row],[Taxes]] -> 37526.4
A40: McKenzie, Michelle | B40: Main | C40: Environmental Compliance | D40: Full Time | E40: 38746 | F40: R | G40: 49360 | H40: 2 | I40: =IF(OR(Table24[[#This Row],[Rating]]=4,Table24[[#This Row],[Rating]]=5), 0.05*Table24[[#This Row],[Salary]],0) -> 0 | J40: =VLOOKUP(Table24[[#This Row],[Salary]],'Tax rates'!A$2:C$8, 2) + VLOOKUP(Table24[[#This Row],[Salary]],'Tax rates'!A$2:C$8, 3) * (Table24[[#This Row],[Salary]] - VLOOKUP(Table24[[#This Row],[Salary]],'Tax rates'!A$2:C$8,1)) -> 6798.7 | K40: =Table24[[#This Row],[Salary]]-Table24[[#This Row],[Taxes]] -> 42561.3
A41: Chang, Gabriel | B41: Main | C41: Environmental Compliance | D41: Half-Time | E41: 40152 | F41: R | G41: 28680 | H41: 1 | I41: =IF(OR(Table24[[#This Row],[Rating]]=4,Table24[[#This Row],[Rating]]=5), 0.05*Table24[[#This Row],[Salary]],0) -> 0 | J41: =VLOOKUP(Table24[[#This Row],[Salary]],'Tax rates'!A$2:C$8, 2) + VLOOKUP(Table24[[#This Row],[Salary]],'Tax rates'!A$2:C$8, 3) * (Table24[[#This Row],[Salary]] - VLOOKUP(Table24[[#This Row],[Salary]],'Tax rates'!A$2:C$8,1)) -> 3251.1 | K41: =Table24[[#This Row],[Salary]]-Table24[[#This Row],[Taxes]] -> 25428.9
A42: Nguyen, Dennis | B42: Main | C42: Environmental Compliance | D42: Hourly | E42: 38961 | G42: 20028 | H42: 4 | I42: =IF(OR(Table24[[#This Row],[Rating]]=4,Table24[[#This Row],[Rating]]=5), 0.05*Table24[[#This Row],[Salary]],0) -> 1001.4 | J42: =VLOOKUP(Table24[[#This Row],[Salary]],'Tax rates'!A$2:C$8, 2) + VLOOKUP(Table24[[#This Row],[Salary]],'Tax rates'!A$2:C$8, 3) * (Table24[[#This Row],[Salary]] - VLOOKUP(Table24[[#This Row],[Salary]],'Tax rates'!A$2:C$8,1)) -> 2212.86 | K42: =Table24[[#This Row],[Salary]]-Table24[[#This Row],[Taxes]] -> 17815.14
A43: Foley, Peter | B43: Main | C43: Environmental Health/Safety | D43: Full Time | E43: 36249 | F43: DMR | G43: 49860 | H43: 2 | I43: =IF(OR(Table24[[#This Row],[Rating]]=4,Table24[[#This Row],[Rating]]=5), 0.05*Table24[[#This Row],[Salary]],0) -> 0 | J43: =VLOOKUP(Table24[[#This Row],[Salary]],'Tax rates'!A$2:C$8, 2) + VLOOKUP(Table24[[#This Row],[Salary]],'Tax rates'!A$2:C$8, 3) * (Table24[[#This Row],[Salary]] - VLOOKUP(Table24[[#This Row],[Salary]],'Tax rates'!A$2:C$8,1)) -> 6908.7 | K43: =Table24[[#This Row],[Salary]]-Table24[[#This Row],[Taxes]] -> 42951.3
A44: Hawkins, Douglas | B44: Main | C44: Environmental Health/Safety | D44: Half-Time | E44: 40516 | F44: R | G44: 28625 | H44: 1 | I44: =IF(OR(Table24[[#This Row],[Rating]]=4,Table24[[#This Row],[Rating]]=5), 0.05*Table24[[#This Row],[Salary]],0) -> 0 | J44: =VLOOKUP(Table24[[#This Row],[Salary]],'Tax rates'!A$2:C$8, 2) + VLOOKUP(Table24[[#This Row],[Salary]],'Tax rates'!A$2:C$8, 3) * (Table24[[#This Row],[Salary]] - VLOOKUP(Table24[[#This Row],[Salary]],'Tax rates'!A$2:C$8,1)) -> 3244.5 | K44: =Table24[[#This Row],[Salary]]-Table24[[#This Row],[Taxes]] -> 25380.5
A45: Hill, Robin | B45: Main | C45: Environmental Health/Safety | D45: Hourly | E45: 40313 | G45: 27484 | H45: 4 | I45: =IF(OR(Table24[[#This Row],[Rating]]=4,Table24[[#This Row],[Rating]]=5), 0.05*Table24[[#This Row],[Salary]],0) -> 1374.2 | J45: =VLOOKUP(Table24[[#This Row],[Salary]],'Tax rates'!A$2:C$8, 2) + VLOOKUP(Table24[[#This Row],[Salary]],'Tax rates'!A$2:C$8, 3) * (Table24[[#This Row],[Salary]] - VLOOKUP(Table24[[#This Row],[Salary]],'Tax rates'!A$2:C$8,1)) -> 3107.58 | K45: =Table24[[#This Row],[Salary]]-Table24[[#This Row],[Taxes]] -> 24376.42
A46: Norton, Bruce | B46: Main | C46: Environmental Health/Safety | D46: Full Time | E46: 38736 | F46: R | G46: 22920 | H46: 3 | I46: =IF(OR(Table24[[#This Row],[Rating]]=4,Table24[[#This Row],[Rating]]=5), 0.05*Table24[[#This Row],[Salary]],0) -> 0 | J46: =VLOOKUP(Table24[[#This Row],[Salary]],'Tax rates'!A$2:C$8, 2) + VLOOKUP(Table24[[#This Row],[Salary]],'Tax rates'!A$2:C$8, 3) * (Table24[[#This Row],[Salary]] - VLOOKUP(Table24[[#This Row],[Salary]],'Tax rates'!A$2:C$8,1)) -> 2559.9 | K46: =Table24[[#This Row],[Salary]]-Table24[[#This Row],[Taxes]] -> 20360.1
A47: Mullins, Angela | B47: Main | C47: Facilities/Engineering | D47: Full Time | E47: 40832 | F47: R | G47: 85920 | H47: 4 | I47: =IF(OR(Table24[[#This Row],[Rating]]=4,Table24[[#This Row],[Rating]]=5), 0.05*Table24[[#This Row],[Salary]],0) -> 4296 | J47: =VLOOKUP(Table24[[#This Row],[Salary]],'Tax rates'!A$2:C$8, 2) + VLOOKUP(Table24[[#This Row],[Salary]],'Tax rates'!A$2:C$8, 3) * (Table24[[#This Row],[Salary]] - VLOOKUP(Table24[[#This Row],[Salary]],'Tax rates'!A$2:C$8,1)) -> 14910.3 | K47: =Table24[[#This Row],[Salary]]-Table24[[#This Row],[Taxes]] -> 71009.7
A48: Briggs, Bryan | B48: Main | C48: Facilities/Engineering | D48: Contract | E48: 35848 | G48: 85480 | H48: 5 | I48: =IF(OR(Table24[[#This Row],[Rating]]=4,Table24[[#This Row],[Rating]]=5), 0.05*Table24[[#This Row],[Salary]],0) -> 4274 | J48: =VLOOKUP(Table24[[#This Row],[Salary]],'Tax rates'!A$2:C$8, 2) + VLOOKUP(Table24[[#This Row],[Salary]],'Tax rates'!A$2:C$8, 3) * (Table24[[#This Row],[Salary]] - VLOOKUP(Table24[[#This Row],[Salary]],'Tax rates'!A$2:C$8,1)) -> 14804.7 | K48: =Table24[[#This Row],[Salary]]-Table24[[#This Row],[Taxes]] -> 70675.3
A49: Dorsey, Matthew | B49: Main | C49: Facilities/Engineering | D49: Full Time | E49: 40501 | F49: M | G49: 77820 | H49: 3 | I49: =IF(OR(Table24[[#This Row],[Rating]]=4,Table24[[#This Row],[Rating]]=5), 0.05*Table24[[#This Row],[Salary]],0) -> 0 | J49: =VLOOKUP(Table24[[#This Row],[Salary]],'Tax rates'!A$2:C$8, 2) + VLOOKUP(Table24[[#This Row],[Salary]],'Tax rates'!A$2:C$8, 3) * (Table24[[#This Row],[Salary]] - VLOOKUP(Table24[[#This Row],[Salary]],'Tax rates'!A$2:C$8,1)) -> 13059.9 | K49: =Table24[[#This Row],[Salary]]-Table24[[#This Row],[Taxes]] -> 64760.1
A50: Cunningham, Denise | B50: Main | C50: Facilities/Engineering | D50: Full Time | E50: 40200 | F50: M | G50: 77350 | H50: 5 | I50: =IF(OR(Table24[[#This Row],[Rating]]=4,Table24[[#This Row],[Rating]]=5), 0.05*Table24[[#This Row],[Salary]],0) -> 3867.5 | J50: =VLOOKUP(Table24[[#This Row],[Salary]],'Tax rates'!A$2:C$8, 2) + VLOOKUP(Table24[[#This Row],[Salary]],'Tax rates'!A$2:C$8, 3) * (Table24[[#This Row],[Salary]] - VLOOKUP(Table24[[#This Row],[Salary]],'Tax rates'!A$2:C$8,1)) -> 12956.5 | K50: =Table24[[#This Row],[Salary]]-Table24[[#This Row],[Taxes]] -> 64393.5
A51: Pruitt, Randy | B51: Main | C51: Facilities/Engineering | D51: Contract | E51: 38792 | G51: 74740 | H51: 5 | I51: =IF(OR(Table24[[#This Row],[Rating]]=4,Table24[[#This Row],[Rating]]=5), 0.05*Table24[[#This Row],[Salary]],0) -> 3737 | J51: =VLOOKUP(Table24[[#This Row],[Salary]],'Tax rates'!A$2:C$8, 2) + VLOOKUP(Table24[[#This Row],[Salary]],'Tax rates'!A$2:C$8, 3) * (Table24[[#This Row],[Salary]] - VLOOKUP(Table24[[#This Row],[Salary]],'Tax rates'!A$2:C$8,1)) -> 12382.3 | K51: =Table24[[#This Row],[Salary]]-Table24[[#This Row],[Taxes]] -> 62357.7
A52: Martinez, Kathleen | B52: Main | C52: Facilities/Engineering | D52: Full Time | E52: 37241 | F52: DMR | G52: 71950 | H52: 5 | I52: =IF(OR(Table24[[#This Row],[Rating]]=4,Table24[[#This Row],[Rating]]=5), 0.05*Table24[[#This Row],[Salary]],0) -> 3597.5 | J52: =VLOOKUP(Table24[[#This Row],[Salary]],'Tax rates'!A$2:C$8, 2) + VLOOKUP(Table24[[#This Row],[Salary]],'Tax rates'!A$2:C$8, 3) * (Table24[[#This Row],[Salary]] - VLOOKUP(Table24[[#This Row],[Salary]],'Tax rates'!A$2:C$8,1)) -> 11768.5 | K52: =Table24[[#This Row],[Salary]]-Table24[[#This Row],[Taxes]] -> 60181.5
A53: Lawrence, Ronald | B53: Main | C53: Facilities/Engineering | D53: Contract | E53: 35902 | G53: 63340 | H53: 3 | I53: =IF(OR(Table24[[#This Row],[Rating]]=4,Table24[[#This Row],[Rating]]=5), 0.05*Table24[[#This Row],[Salary]],0) -> 0 | J53: =VLOOKUP(Table24[[#This Row],[Salary]],'Tax rates'!A$2:C$8, 2) + VLOOKUP(Table24[[#This Row],[Salary]],'Tax rates'!A$2:C$8, 3) * (Table24[[#This Row],[Salary]] - VLOOKUP(Table24[[#This Row],[Salary]],'Tax rates'!A$2:C$8,1)) -> 9874.3 | K53: =Table24[[#This Row],[Salary]]-Table24[[#This Row],[Taxes]] -> 53465.7
A54: Fletcher, Brian | B54: Main | C54: Facilities/Engineering | D54: Full Time | E54: 37176 | F54: M | G54: 62790 | H54: 2 | I54: =IF(OR(Table24[[#This Row],[Rating]]=4,Table24[[#This Row],[Rating]]=5), 0.05*Table24[[#This Row],[Salary]],0) -> 0 | J54: =VLOOKUP(Table24[[#This Row],[Salary]],'Tax rates'!A$2:C$8, 2) + VLOOKUP(Table24[[#This Row],[Salary]],'Tax rates'!A$2:C$8, 3) * (Table24[[#This Row],[Salary]] - VLOOKUP(Table24[[#This Row],[Salary]],'Tax rates'!A$2:C$8,1)) -> 9753.3 | K54: =Table24[[#This Row],[Salary]]-Table24[[#This Row],[Taxes]] -> 53036.7
A55: Hammond, Robert | B55: Main | C55: Facilities/Engineering | D55: Full Time | E55: 40880 | F55: DM | G55: 61400 | H55: 5 | I55: =IF(OR(Table24[[#This Row],[Rating]]=4,Table24[[#This Row],[Rating]]=5), 0.05*Table24[[#This Row],[Salary]],0) -> 3070 | J55: =VLOOKUP(Table24[[#This Row],[Salary]],'Tax rates'!A$2:C$8, 2) + VLOOKUP(Table24[[#This Row],[Salary]],'Tax rates'!A$2:C$8, 3) * (Table24[[#This Row],[Salary]] - VLOOKUP(Table24[[#This Row],[Salary]],'Tax rates'!A$2:C$8,1)) -> 9447.5 | K55: =Table24[[#This Row],[Salary]]-Table24[[#This Row],[Taxes]] -> 51952.5
A56: Gardner, Anthony | B56: Main | C56: Facilities/Engineering | D56: Contract | E56: 39803 | G56: 42940 | H56: 1 | I56: =IF(OR(Table24[[#This Row],[Rating]]=4,Table24[[#This Row],[Rating]]=5), 0.05*Table24[[#This Row],[Salary]],0) -> 0 | J56: =VLOOKUP(Table24[[#This Row],[Salary]],'Tax rates'!A$2:C$8, 2) + VLOOKUP(Table24[[#This Row],[Salary]],'Tax rates'!A$2:C$8, 3) * (Table24[[#This Row],[Salary]] - VLOOKUP(Table24[[#This Row],[Salary]],'Tax rates'!A$2:C$8,1)) -> 5386.3 | K56: =Table24[[#This Row],[Salary]]-Table24[[#This Row],[Taxes]] -> 37553.7
A57: Porter, Rachel | B57: Main | C57: Facilities/Engineering | D57: Full Time | E57: 40085 | F57: DMR | G57: 41490 | H57: 5 | I57: =IF(OR(Table24[[#This Row],[Rating]]=4,Table24[[#This Row],[Rating]]=5), 0.05*Table24[[#This Row],[Salary]],0) -> 2074.5 | J57: =VLOOKUP(Table24[[#This Row],[Salary]],'Tax rates'!A$2:C$8, 2) + VLOOKUP(Table24[[#This Row],[Salary]],'Tax rates'!A$2:C$8, 3) * (Table24[[#This Row],[Salary]] - VLOOKUP(Table24[[#This Row],[Salary]],'Tax rates'!A$2:C$8,1)) -> 5067.3 | K57: =Table24[[#This Row],[Salary]]-Table24[[#This Row],[Taxes]] -> 36422.7
A58: Swanson, Vicki | B58: Main | C58: Facilities/Engineering | D58: Full Time | E58: 40274 | F58: DM | G58: 38730 | H58: 1 | I58: =IF(OR(Table24[[#This Row],[Rating]]=4,Table24[[#This Row],[Rating]]=5), 0.05*Table24[[#This Row],[Salary]],0) -> 0 | J58: =VLOOKUP(Table24[[#This Row],[Salary]],'Tax rates'!A$2:C$8, 2) + VLOOKUP(Table24[[#This Row],[Salary]],'Tax rates'!A$2:C$8, 3) * (Table24[[#This Row],[Salary]] - VLOOKUP(Table24[[#This Row],[Salary]],'Tax rates'!A$2:C$8,1)) -> 4460.1 | K58: =Table24[[#This Row],[Salary]]-Table24[[#This Row],[Taxes]] -> 34269.9
A59: Flowers, Kathleen | B59: Main | C59: Facilities/Engineering | D59: Full Time | E59: 39215 | F59: DMR | G59: 31910 | H59: 5 | I59: =IF(OR(Table24[[#This Row],[Rating]]=4,Table24[[#This Row],[Rating]]=5), 0.05*Table24[[#This Row],[Salary]],0) -> 1595.5 | J59: =VLOOKUP(Table24[[#This Row],[Salary]],'Tax rates'!A$2:C$8, 2) + VLOOKUP(Table24[[#This Row],[Salary]],'Tax rates'!A$2:C$8, 3) * (Table24[[#This Row],[Salary]] - VLOOKUP(Table24[[#This Row],[Salary]],'Tax rates'!A$2:C$8,1)) -> 3638.7 | K59: =Table24[[#This Row],[Salary]]-Table24[[#This Row],[Taxes]] -> 28271.3
A60: Schneider, Gay | B60: Main | C60: Facilities/Engineering | D60: Half-Time | E60: 39279 | F60: DMR | G60: 26890 | H60: 3 | I60: =IF(OR(Table24[[#This Row],[Rating]]=4,Table24[[#This Row],[Rating]]=5), 0.05*Table24[[#This Row],[Salary]],0) -> 0 | J60: =VLOOKUP(Table24[[#This Row],[Salary]],'Tax rates'!A$2:C$8, 2) + VLOOKUP(Table24[[#This Row],[Salary]],'Tax rates'!A$2:C$8, 3) * (Table24[[#This Row],[Salary]] - VLOOKUP(Table24[[#This Row],[Salary]],'Tax rates'!A$2:C$8,1)) -> 3036.3 | K60: =Table24[[#This Row],[Salary]]-Table24[[#This Row],[Taxes]] -> 23853.7
A61: Navarro, Marc | B61: Main | C61: Facilities/Engineering | D61: Half-Time | E61: 35842 | F61: D | G61: 23380 | H61: 4 | I61: =IF(OR(Table24[[#This Row],[Rating]]=4,Table24[[#This Row],[Rating]]=5), 0.05*Table24[[#This Row],[Salary]],0) -> 1169 | J61: =VLOOKUP(Table24[[#This Row],[Salary]],'Tax rates'!A$2:C$8, 2) + VLOOKUP(Table24[[#This Row],[Salary]],'Tax rates'!A$2:C$8, 3) * (Table24[[#This Row],[Salary]] - VLOOKUP(Table24[[#This Row],[Salary]],'Tax rates'!A$2:C$8,1)) -> 2615.1 | K61: =Table24[[#This Row],[Salary]]-Table24[[#This Row],[Taxes]] -> 20764.9
A62: Cortez, Jack | B62: Main | C62: Green Building | D62: Full Time | E62: 39492 | F62: DMR | G62: 36630 | H62: 4 | I62: =IF(OR(Table24[[#This Row],[Rating]]=4,Table24[[#This Row],[Rating]]=5), 0.05*Table24[[#This Row],[Salary]],0) -> 1831.5 | J62: =VLOOKUP(Table24[[#This Row],[Salary]],'Tax rates'!A$2:C$8, 2) + VLOOKUP(Table24[[#This Row],[Salary]],'Tax rates'!A$2:C$8, 3) * (Table24[[#This Row],[Salary]] - VLOOKUP(Table24[[#This Row],[Salary]],'Tax rates'!A$2:C$8,1)) -> 4205.1 | K62: =Table24[[#This Row],[Salary]]-Table24[[#This Row],[Taxes]] -> 32424.9
A63: Pacheco, Therese | B63: Main | C63: Green Building | D63: Contract | E63: 39529 | G63: 35620 | H63: 4 | I63: =IF(OR(Table24[[#This Row],[Rating]]=4,Table24[[#This Row],[Rating]]=5), 0.05*Table24[[#This Row],[Salary]],0) -> 1781 | J63: =VLOOKUP(Table24[[#This Row],[Salary]],'Tax rates'!A$2:C$8, 2) + VLOOKUP(Table24[[#This Row],[Salary]],'Tax rates'!A$2:C$8, 3) * (Table24[[#This Row],[Salary]] - VLOOKUP(Table24[[#This Row],[Salary]],'Tax rates'!A$2:C$8,1)) -> 4083.9 | K63: =Table24[[#This Row],[Salary]]-Table24[[#This Row],[Taxes]] -> 31536.1
A64: Ramos, Jan | B64: Main | C64: Human Resources | D64: Full Time | E64: 40442 | F64: DMR | G64: 66740 | H64: 2 | I64: =IF(OR(Table24[[#This Row],[Rating]]=4,Table24[[#This Row],[Rating]]=5), 0.05*Table24[[#This Row],[Salary]],0) -> 0 | J64: =VLOOKUP(Table24[[#This Row],[Salary]],'Tax rates'!A$2:C$8, 2) + VLOOKUP(Table24[[#This Row],[Salary]],'Tax rates'!A$2:C$8, 3) * (Table24[[#This Row],[Salary]] - VLOOKUP(Table24[[#This Row],[Salary]],'Tax rates'!A$2:C$8,1)) -> 10622.3 | K64: =Table24[[#This Row],[Salary]]-Table24[[#This Row],[Taxes]] -> 56117.7
A65: Wall, John | B65: Main | C65: Human Resources | D65: Contract | E65: 38854 | G65: 44820 | H65: 4 | I65: =IF(OR(Table24[[#This Row],[Rating]]=4,Table24[[#This Row],[Rating]]=5), 0.05*Table24[[#This Row],[Salary]],0) -> 2241 | J65: =VLOOKUP(Table24[[#This Row],[Salary]],'Tax rates'!A$2:C$8, 2) + VLOOKUP(Table24[[#This Row],[Salary]],'Tax rates'!A$2:C$8, 3) * (Table24[[#This Row],[Salary]] - VLOOKUP(Table24[[#This Row],[Salary]],'Tax rates'!A$2:C$8,1)) -> 5799.9 | K65: =Table24[[#This Row],[Salary]]-Table24[[#This Row],[Taxes]] -> 39020.1
A66: Best, Lara | B66: Main | C66: IT | D66: Full Time | E66: 38227 | F66: R | G66: 86200 | H66: 3 | I66: =IF(OR(Table24[[#This Row],[Rating]]=4,Table24[[#This Row],[Rating]]=5), 0.05*Table24[[#This Row],[Salary]],0) -> 0 | J66: =VLOOKUP(Table24[[#This Row],[Salary]],'Tax rates'!A$2:C$8, 2) + VLOOKUP(Table24[[#This Row],[Salary]],'Tax rates'!A$2:C$8, 3) * (Table24[[#This Row],[Salary]] - VLOOKUP(Table24[[#This Row],[Salary]],'Tax rates'!A$2:C$8,1)) -> 14977.5 | K66: =Table24[[#This Row],[Salary]]-Table24[[#This Row],[Taxes]] -> 71222.5
A67: Mack, Barry | B67: Main | C67: IT | D67: Full Time | E67: 40525 | F67: DM | G67: 77950 | H67: 4 | I67: =IF(OR(Table24[[#This Row],[Rating]]=4,Table24[[#This Row],[Rating]]=5), 0.05*Table24[[#This Row],[Salary]],0) -> 3897.5 | J67: =VLOOKUP(Table24[[#This Row],[Salary]],'Tax rates'!A$2:C$8, 2) + VLOOKUP(Table24[[#This Row],[Salary]],'Tax rates'!A$2:C$8, 3) * (Table24[[#This Row],[Salary]] - VLOOKUP(Table24[[#This Row],[Salary]],'Tax rates'!A$2:C$8,1)) -> 13088.5 | K67: =Table24[[#This Row],[Salary]]-Table24[[#This Row],[Taxes]] -> 64861.5
A68: Russell, Mark | B68: Main | C68: IT | D68: Full Time | E68: 35969 | F68: DMR | G68: 74530 | H68: 5 | I68: =IF(OR(Table24[[#This Row],[Rating]]=4,Table24[[#This Row],[Rating]]=5), 0.05*Table24[[#This Row],[Salary]],0) -> 3726.5 | J68: =VLOOKUP(Table24[[#This Row],[Salary]],'Tax rates'!A$2:C$8, 2) + VLOOKUP(Table24[[#This Row],[Salary]],'Tax rates'!A$2:C$8, 3) * (Table24[[#This Row],[Salary]] - VLOOKUP(Table24[[#This Row],[Salary]],'Tax rates'!A$2:C$8,1)) -> 12336.1 | K68: =Table24[[#This Row],[Salary]]-Table24[[#This Row],[Taxes]] -> 62193.9
A69: Skinner, Jason | B69: Main | C69: IT | D69: Full Time | E69: 39224 | F69: R | G69: 73030 | H69: 5 | I69: =IF(OR(Table24[[#This Row],[Rating]]=4,Table24[[#This Row],[Rating]]=5), 0.05*Table24[[#This Row],[Salary]],0) -> 3651.5 | J69: =VLOOKUP(Table24[[#This Row],[Salary]],'Tax rates'!A$2:C$8, 2) + VLOOKUP(Table24[[#This Row],[Salary]],'Tax rates'!A$2:C$8, 3) * (Table24[[#This Row],[Salary]] - VLOOKUP(Table24[[#This Row],[Salary]],'Tax rates'!A$2:C$8,1)) -> 12006.1 | K69: =Table24[[#This Row],[Salary]]-Table24[[#This Row],[Taxes]] -> 61023.9
A70: Peterson, Shaun | B70: Main | C70: IT | D70: Full Time | E70: 41186 | F70: D | G70: 46910 | H70: 3 | I70: =IF(OR(Table24[[#This Row],[Rating]]=4,Table24[[#This Row],[Rating]]=5), 0.05*Table24[[#This Row],[Salary]],0) -> 0 | J70: =VLOOKUP(Table24[[#This Row],[Salary]],'Tax rates'!A$2:C$8, 2) + VLOOKUP(Table24[[#This Row],[Salary]],'Tax rates'!A$2:C$8, 3) * (Table24[[#This Row],[Salary]] - VLOOKUP(Table24[[#This Row],[Salary]],'Tax rates'!A$2:C$8,1)) -> 6259.7 | K70: =Table24[[#This Row],[Salary]]-Table24[[#This Row],[Taxes]] -> 40650.3
A71: Wong, Dennis | B71: Main | C71: IT | D71: Full Time | E71: 40883 | F71: DMR | G71: 43580 | H71: 5 | I71: =IF(OR(Table24[[#This Row],[Rating]]=4,Table24[[#This Row],[Rating]]=5), 0.05*Table24[[#This Row],[Salary]],0) -> 2179 | J71: =VLOOKUP(Table24[[#This Row],[Salary]],'Tax rates'!A$2:C$8, 2) + VLOOKUP(Table24[[#This Row],[Salary]],'Tax rates'!A$2:C$8, 3) * (Table24[[#This Row],[Salary]] - VLOOKUP(Table24[[#This Row],[Salary]],'Tax rates'!A$2:C$8,1)) -> 5527.1 | K71: =Table24[[#This Row],[Salary]]-Table24[[#This Row],[Taxes]] -> 38052.9
A72: Chandler, Diane | B72: Main | C72: IT | D72: Hourly | E72: 36329 | G72: 39764 | H72: 1 | I72: =IF(OR(Table24[[#This Row],[Rating]]=4,Table24[[#This Row],[Rating]]=5), 0.05*Table24[[#This Row],[Salary]],0) -> 0 | J72: =VLOOKUP(Table24[[#This Row],[Salary]],'Tax rates'!A$2:C$8, 2) + VLOOKUP(Table24[[#This Row],[Salary]],'Tax rates'!A$2:C$8, 3) * (Table24[[#This Row],[Salary]] - VLOOKUP(Table24[[#This Row],[Salary]],'Tax rates'!A$2:C$8,1)) -> 4687.58 | K72: =Table24[[#This Row],[Salary]]-Table24[[#This Row],[Taxes]] -> 35076.42
A73: Alvarado, Sonia | B73: Main | C73: IT | D73: Half-Time | E73: 40807 | F73: DM | G73: 35045 | H73: 4 | I73: =IF(OR(Table24[[#This Row],[Rating]]=4,Table24[[#This Row],[Rating]]=5), 0.05*Table24[[#This Row],[Salary]],0) -> 1752.25 | J73: =VLOOKUP(Table24[[#This Row],[Salary]],'Tax rates'!A$2:C$8, 2) + VLOOKUP(Table24[[#This Row],[Salary]],'Tax rates'!A$2:C$8, 3) * (Table24[[#This Row],[Salary]] - VLOOKUP(Table24[[#This Row],[Salary]],'Tax rates'!A$2:C$8,1)) -> 4014.9 | K73: =Table24[[#This Row],[Salary]]-Table24[[#This Row],[Taxes]] -> 31030.1
A74: Pace, Joseph | B74: Main | C74: IT | D74: Contract | E74: 36623 | G74: 30300 | H74: 1 | I74: =IF(OR(Table24[[#This Row],[Rating]]=4,Table24[[#This Row],[Rating]]=5), 0.05*Table24[[#This Row],[Salary]],0) -> 0 | J74: =VLOOKUP(Table24[[#This Row],[Salary]],'Tax rates'!A$2:C$8, 2) + VLOOKUP(Table24[[#This Row],[Salary]],'Tax rates'!A$2:C$8, 3) * (Table24[[#This Row],[Salary]] - VLOOKUP(Table24[[#This Row],[Salary]],'Tax rates'!A$2:C$8,1)) -> 3445.5 | K74: =Table24[[#This Row],[Salary]]-Table24[[#This Row],[Taxes]] -> 26854.5
A75: Morris, Richelle | B75: Main | C75: IT | D75: Full Time | E75: 39284 | F75: DMR | G75: 25830 | H75: 5 | I75: =IF(OR(Table24[[#This Row],[Rating]]=4,Table24[[#This Row],[Rating]]=5), 0.05*Table24[[#This Row],[Salary]],0) -> 1291.5 | J75: =VLOOKUP(Table24[[#This Row],[Salary]],'Tax rates'!A$2:C$8, 2) + VLOOKUP(Table24[[#This Row],[Salary]],'Tax rates'!A$2:C$8, 3) * (Table24[[#This Row],[Salary]] - VLOOKUP(Table24[[#This Row],[Salary]],'Tax rates'!A$2:C$8,1)) -> 2909.1 | K75: =Table24[[#This Row],[Salary]]-Table24[[#This Row],[Taxes]] -> 22920.9
A76: Banks, Ryan | B76: Main | C76: IT | D76: Hourly | E76: 37711 | G76: 21648 | H76: 2 | I76: =IF(OR(Table24[[#This Row],[Rating]]=4,Table24[[#This Row],[Rating]]=5), 0.05*Table24[[#This Row],[Salary]],0) -> 0 | J76: =VLOOKUP(Table24[[#This Row],[Salary]],'Tax rates'!A$2:C$8, 2) + VLOOKUP(Table24[[#This Row],[Salary]],'Tax rates'!A$2:C$8, 3) * (Table24[[#This Row],[Salary]] - VLOOKUP(Table24[[#This Row],[Salary]],'Tax rates'!A$2:C$8,1)) -> 2407.26 | K76: =Table24[[#This Row],[Salary]]-Table24[[#This Row],[Taxes]] -> 19240.74
A77: Hines, Herb | B77: Main | C77: IT | D77: Hourly | E77: 40452 | G77: 9180 | H77: 3 | I77: =IF(OR(Table24[[#This Row],[Rating]]=4,Table24[[#This Row],[Rating]]=5), 0.05*Table24[[#This Row],[Salary]],0) -> 0 | J77: =VLOOKUP(Table24[[#This Row],[Salary]],'Tax rates'!A$2:C$8, 2) + VLOOKUP(Table24[[#This Row],[Salary]],'Tax rates'!A$2:C$8, 3) * (Table24[[#This Row],[Salary]] - VLOOKUP(Table24[[#This Row],[Salary]],'Tax rates'!A$2:C$8,1)) -> 918 | K77: =Table24[[#This Row],[Salary]]-Table24[[#This Row],[Taxes]] -> 8262
A78: Tran, Chad | B78: Main | C78: Major Mfg Projects | D78: Half-Time | E78: 39515 | F78: M | G78: 89780 | H78: 4 | I78: =IF(OR(Table24[[#This Row],[Rating]]=4,Table24[[#This Row],[Rating]]=5), 0.05*Table24[[#This Row],[Salary]],0) -> 4489 | J78: =VLOOKUP(Table24[[#This Row],[Salary]],'Tax rates'!A$2:C$8, 2) + VLOOKUP(Table24[[#This Row],[Salary]],'Tax rates'!A$2:C$8, 3) * (Table24[[#This Row],[Salary]] - VLOOKUP(Table24[[#This Row],[Salary]],'Tax rates'!A$2:C$8,1)) -> 15836.7 | K78: =Table24[[#This Row],[Salary]]-Table24[[#This Row],[Taxes]] -> 73943.3
A79: Romero, Randy | B79: Main | C79: Major Mfg Projects | D79: Full Time | E79: 40690 | F79: DMR | G79: 89140 | H79: 1 | I79: =IF(OR(Table24[[#This Row],[Rating]]=4,Table24[[#This Row],[Rating]]=5), 0.05*Table24[[#This Row],[Salary]],0) -> 0 | J79: =VLOOKUP(Table24[[#This Row],[Salary]],'Tax rates'!A$2:C$8, 2) + VLOOKUP(Table24[[#This Row],[Salary]],'Tax rates'!A$2:C$8, 3) * (Table24[[#This Row],[Salary]] - VLOOKUP(Table24[[#This Row],[Salary]],'Tax rates'!A$2:C$8,1)) -> 15683.1 | K79: =Table24[[#This Row],[Salary]]-Table24[[#This Row],[Taxes]] -> 73456.9
A80: Campos, Richard | B80: Main | C80: Major Mfg Projects | D80: Hourly | E80: 36519 | F80: R | G80: 61860 | H80: 5 | I80: =IF(OR(Table24[[#This Row],[Rating]]=4,Table24[[#This Row],[Rating]]=5), 0.05*Table24[[#This Row],[Salary]],0) -> 3093 | J80: =VLOOKUP(Table24[[#This Row],[Salary]],'Tax rates'!A$2:C$8, 2) + VLOOKUP(Table24[[#This Row],[Salary]],'Tax rates'!A$2:C$8, 3) * (Table24[[#This Row],[Salary]] - VLOOKUP(Table24[[#This Row],[Salary]],'Tax rates'!A$2:C$8,1)) -> 9548.7 | K80: =Table24[[#This Row],[Salary]]-Table24[[#This Row],[Taxes]] -> 52311.3
A81: Parrish, Debra | B81: Main | C81: Manufacturing | D81: Full Time | E81: 36101 | F81: DMR | G81: 88240 | H81: 5 | I81: =IF(OR(Table24[[#This Row],[Rating]]=4,Table24[[#This Row],[Rating]]=5), 0.05*Table24[[#This Row],[Salary]],0) -> 4412 | J81: =VLOOKUP(Table24[[#This Row],[Salary]],'Tax rates'!A$2:C$8, 2) + VLOOKUP(Table24[[#This Row],[Salary]],'Tax rates'!A$2:C$8, 3) * (Table24[[#This Row],[Salary]] - VLOOKUP(Table24[[#This Row],[Salary]],'Tax rates'!A$2:C$8,1)) -> 15467.1 | K81: =Table24[[#This Row],[Salary]]-Table24[[#This Row],[Taxes]] -> 72772.9
A82: Smith, Koleen | B82: Main | C82: Manufacturing | D82: Full Time | E82: 40269 | F82: R | G82: 86260 | H82: 3 | I82: =IF(OR(Table24[[#This Row],[Rating]]=4,Table24[[#This Row],[Rating]]=5), 0.05*Table24[[#This Row],[Salary]],0) -> 0 | J82: =VLOOKUP(Table24[[#This Row],[Salary]],'Tax rates'!A$2:C$8, 2) + VLOOKUP(Table24[[#This Row],[Salary]],'Tax rates'!A$2:C$8, 3) * (Table24[[#This Row],[Salary]] - VLOOKUP(Table24[[#This Row],[Salary]],'Tax rates'!A$2:C$8,1)) -> 14991.9 | K82: =Table24[[#This Row],[Salary]]-Table24[[#This Row],[Taxes]] -> 71268.1
A83: Perez, Kim | B83: Main | C83: Manufacturing | D83: Contract | E83: 39545 | G83: 84170 | H83: 2 | I83: =IF(OR(Table24[[#This Row],[Rating]]=4,Table24[[#This Row],[Rating]]=5), 0.05*Table24[[#This Row],[Salary]],0) -> 0 | J83: =VLOOKUP(Table24[[#This Row],[Salary]],'Tax rates'!A$2:C$8, 2) + VLOOKUP(Table24[[#This Row],[Salary]],'Tax rates'!A$2:C$8, 3) * (Table24[[#This Row],[Salary]] - VLOOKUP(Table24[[#This Row],[Salary]],'Tax rates'!A$2:C$8,1)) -> 14490.3 | K83: =Table24[[#This Row],[Salary]]-Table24[[#This Row],[Taxes]] -> 69679.7
A84: Hampton, Catherine | B84: Main | C84: Manufacturing | D84: Full Time | E84: 39264 | F84: R | G84: 81980 | H84: 2 | I84: =IF(OR(Table24[[#This Row],[Rating]]=4,Table24[[#This Row],[Rating]]=5), 0.05*Table24[[#This Row],[Salary]],0) -> 0 | J84: =VLOOKUP(Table24[[#This Row],[Salary]],'Tax rates'!A$2:C$8, 2) + VLOOKUP(Table24[[#This Row],[Salary]],'Tax rates'!A$2:C$8, 3) * (Table24[[#This Row],[Salary]] - VLOOKUP(Table24[[#This Row],[Salary]],'Tax rates'!A$2:C$8,1)) -> 13975.1 | K84: =Table24[[#This Row],[Salary]]-Table24[[#This Row],[Taxes]] -> 68004.9
A85: Allen, Thomas | B85: Main | C85: Manufacturing | D85: Full Time | E85: 38807 | F85: DMR | G85: 79730 | H85: 2 | I85: =IF(OR(Table24[[#This Row],[Rating]]=4,Table24[[#This Row],[Rating]]=5), 0.05*Table24[[#This Row],[Salary]],0) -> 0 | J85: =VLOOKUP(Table24[[#This Row],[Salary]],'Tax rates'!A$2:C$8, 2) + VLOOKUP(Table24[[#This Row],[Salary]],'Tax rates'!A$2:C$8, 3) * (Table24[[#This Row],[Salary]] - VLOOKUP(Table24[[#This Row],[Salary]],'Tax rates'!A$2:C$8,1)) -> 13480.1 | K85: =Table24[[#This Row],[Salary]]-Table24[[#This Row],[Taxes]] -> 66249.9
A86: Patel, Donald | B86: Main | C86: Manufacturing | D86: Full Time | E86: 36535 | F86: DMR | G86: 76192 | H86: 4 | I86: =IF(OR(Table24[[#This Row],[Rating]]=4,Table24[[#This Row],[Rating]]=5), 0.05*Table24[[#This Row],[Salary]],0) -> 3809.6 | J86: =VLOOKUP(Table24[[#This Row],[Salary]],'Tax rates'!A$2:C$8, 2) + VLOOKUP(Table24[[#This Row],[Salary]],'Tax rates'!A$2:C$8, 3) * (Table24[[#This Row],[Salary]] - VLOOKUP(Table24[[#This Row],[Salary]],'Tax rates'!A$2:C$8,1)) -> 12701.74 | K86: =Table24[[#This Row],[Salary]]-Table24[[#This Row],[Taxes]] -> 63490.26
A87: Day, David | B87: Main | C87: Manufacturing | D87: Full Time | E87: 37943 | F87: DMR | G87: 75176 | H87: 3 | I87: =IF(OR(Table24[[#This Row],[Rating]]=4,Table24[[#This Row],[Rating]]=5), 0.05*Table24[[#This Row],[Salary]],0) -> 0 | J87: =VLOOKUP(Table24[[#This Row],[Salary]],'Tax rates'!A$2:C$8, 2) + VLOOKUP(Table24[[#This Row],[Salary]],'Tax rates'!A$2:C$8, 3) * (Table24[[#This Row],[Salary]] - VLOOKUP(Table24[[#This Row],[Salary]],'Tax rates'!A$2:C$8,1)) -> 12478.22 | K87: =Table24[[#This Row],[Salary]]-Table24[[#This Row],[Taxes]] -> 62697.78
A88: Stafford, Rhonda | B88: Main | C88: Manufacturing | D88: Full Time | E88: 36009 | F88: DMR | G88: 75120 | H88: 5 | I88: =IF(OR(Table24[[#This Row],[Rating]]=4,Table24[[#This Row],[Rating]]=5), 0.05*Table24[[#This Row],[Salary]],0) -> 3756 | J88: =VLOOKUP(Table24[[#This Row],[Salary]],'Tax rates'!A$2:C$8, 2) + VLOOKUP(Table24[[#This Row],[Salary]],'Tax rates'!A$2:C$8, 3) * (Table24[[#This Row],[Salary]] - VLOOKUP(Table24[[#This Row],[Salary]],'Tax rates'!A$2:C$8,1)) -> 12465.9 | K88: =Table24[[#This Row],[Salary]]-Table24[[#This Row],[Taxes]] -> 62654.1
A89: Pierce, Karen | B89: Main | C89: Manufacturing | D89: Contract | E89: 39092 | G89: 73990 | H89: 3 | I89: =IF(OR(Table24[[#This Row],[Rating]]=4,Table24[[#This Row],[Rating]]=5), 0.05*Table24[[#This Row],[Salary]],0) -> 0 | J89: =VLOOKUP(Table24[[#This Row],[Salary]],'Tax rates'!A$2:C$8, 2) + VLOOKUP(Table24[[#This Row],[Salary]],'Tax rates'!A$2:C$8, 3) * (Table24[[#This Row],[Salary]] - VLOOKUP(Table24[[#This Row],[Salary]],'Tax rates'!A$2:C$8,1)) -> 12217.3 | K89: =Table24[[#This Row],[Salary]]-Table24[[#This Row],[Taxes]] -> 61772.7
A90: Nash, Mark | B90: Main | C90: Manufacturing | D90: Full Time | E90: 39390 | F90: M | G90: 71490 | H90: 5 | I90: =IF(OR(Table24[[#This Row],[Rating]]=4,Table24[[#This Row],[Rating]]=5), 0.05*Table24[[#This Row],[Salary]],0) -> 3574.5 | J90: =VLOOKUP(Table24[[#This Row],[Salary]],'Tax rates'!A$2:C$8, 2) + VLOOKUP(Table24[[#This Row],[Salary]],'Tax rates'!A$2:C$8, 3) * (Table24[[#This Row],[Salary]] - VLOOKUP(Table24[[#This Row],[Salary]],'Tax rates'!A$2:C$8,1)) -> 11667.3 | K90: =Table24[[#This Row],[Salary]]-Table24[[#This Row],[Taxes]] -> 59822.7
A91: Bradley, David | B91: Main | C91: Manufacturing | D91: Full Time | E91: 39696 | F91: DMR | G91: 69320 | H91: 3 | I91: =IF(OR(Table24[[#This Row],[Rating]]=4,Table24[[#This Row],[Rating]]=5), 0.05*Table24[[#This Row],[Salary]],0) -> 0 | J91: =VLOOKUP(Table24[[#This Row],[Salary]],'Tax rates'!A$2:C$8, 2) + VLOOKUP(Table24[[#This Row],[Salary]],'Tax rates'!A$2:C$8, 3) * (Table24[[#This Row],[Salary]] - VLOOKUP(Table24[[#This Row],[Salary]],'Tax rates'!A$2:C$8,1)) -> 11189.9 | K91: =Table24[[#This Row],[Salary]]-Table24[[#This Row],[Taxes]] -> 58130.1
A92: Snow, Desiree | B92: Main | C92: Manufacturing | D92: Full Time | E92: 37509 | F92: R | G92: 69080 | H92: 3 | I92: =IF(OR(Table24[[#This Row],[Rating]]=4,Table24[[#This Row],[Rating]]=5), 0.05*Table24[[#This Row],[Salary]],0) -> 0 | J92: =VLOOKUP(Table24[[#This Row],[Salary]],'Tax rates'!A$2:C$8, 2) + VLOOKUP(Table24[[#This Row],[Salary]],'Tax rates'!A$2:C$8, 3) * (Table24[[#This Row],[Salary]] - VLOOKUP(Table24[[#This Row],[Salary]],'Tax rates'!A$2:C$8,1)) -> 11137.1 | K92: =Table24[[#This Row],[Salary]]-Table24[[#This Row],[Taxes]] -> 57942.9
A93: Chambers, Richard | B93: Main | C93: Manufacturing | D93: Contract | E93: 35992 | G93: 68260 | H93: 5 | I93: =IF(OR(Table24[[#This Row],[Rating]]=4,Table24[[#This Row],[Rating]]=5), 0.05*Table24[[#This Row],[Salary]],0) -> 3413 | J93: =VLOOKUP(Table24[[#This Row],[Salary]],'Tax rates'!A$2:C$8, 2) + VLOOKUP(Table24[[#This Row],[Salary]],'Tax rates'!A$2:C$8, 3) * (Table24[[#This Row],[Salary]] - VLOOKUP(Table24[[#This Row],[Salary]],'Tax rates'!A$2:C$8,1)) -> 10956.7 | K93: =Table24[[#This Row],[Salary]]-Table24[[#This Row],[Taxes]] -> 57303.3
A94: Patrick, Wendy | B94: Main | C94: Manufacturing | D94: Contract | E94: 40492 | G94: 66010 | H94: 2 | I94: =IF(OR(Table24[[#This Row],[Rating]]=4,Table24[[#This Row],[Rating]]=5), 0.05*Table24[[#This Row],[Salary]],0) -> 0 | J94: =VLOOKUP(Table24[[#This Row],[Salary]],'Tax rates'!A$2:C$8, 2) + VLOOKUP(Table24[[#This Row],[Salary]],'Tax rates'!A$2:C$8, 3) * (Table24[[#This Row],[Salary]] - VLOOKUP(Table24[[#This Row],[Salary]],'Tax rates'!A$2:C$8,1)) -> 10461.7 | K94: =Table24[[#This Row],[Salary]]-Table24[[#This Row],[Taxes]] -> 55548.3
A95: Little, Steve | B95: Main | C95: Manufacturing | D95: Full Time | E95: 37436 | F95: M | G95: 64130 | H95: 1 | I95: =IF(OR(Table24[[#This Row],[Rating]]=4,Table24[[#This Row],[Rating]]=5), 0.05*Table24[[#This Row],[Salary]],0) -> 0 | J95: =VLOOKUP(Table24[[#This Row],[Salary]],'Tax rates'!A$2:C$8, 2) + VLOOKUP(Table24[[#This Row],[Salary]],'Tax rates'!A$2:C$8, 3) * (Table24[[#This Row],[Salary]] - VLOOKUP(Table24[[#This Row],[Salary]],'Tax rates'!A$2:C$8,1)) -> 10048.1 | K95: =Table24[[#This Row],[Salary]]-Table24[[#This Row],[Taxes]] -> 54081.9
A96: McConnell, Justin | B96: Main | C96: Manufacturing | D96: Contract | E96: 39539 | G96: 63310 | H96: 3 | I96: =IF(OR(Table24[[#This Row],[Rating]]=4,Table24[[#This Row],[Rating]]=5), 0.05*Table24[[#This Row],[Salary]],0) -> 0 | J96: =VLOOKUP(Table24[[#This Row],[Salary]],'Tax rates'!A$2:C$8, 2) + VLOOKUP(Table24[[#This Row],[Salary]],'Tax rates'!A$2:C$8, 3) * (Table24[[#This Row],[Salary]] - VLOOKUP(Table24[[#This Row],[Salary]],'Tax rates'!A$2:C$8,1)) -> 9867.7 | K96: =Table24[[#This Row],[Salary]]-Table24[[#This Row],[Taxes]] -> 53442.3
A97: Stewart, Elizabeth | B97: Main | C97: Manufacturing | D97: Full Time | E97: 37331 | F97: R | G97: 62750 | H97: 3 | I97: =IF(OR(Table24[[#This Row],[Rating]]=4,Table24[[#This Row],[Rating]]=5), 0.05*Table24[[#This Row],[Salary]],0) -> 0 | J97: =VLOOKUP(Table24[[#This Row],[Salary]],'Tax rates'!A$2:C$8, 2) + VLOOKUP(Table24[[#This Row],[Salary]],'Tax rates'!A$2:C$8, 3) * (Table24[[#This Row],[Salary]] - VLOOKUP(Table24[[#This Row],[Salary]],'Tax rates'!A$2:C$8,1)) -> 9744.5 | K97: =Table24[[#This Row],[Salary]]-Table24[[#This Row],[Taxes]] -> 53005.5
A98: Wright, Brad | B98: Main | C98: Manufacturing | D98: Full Time | E98: 36273 | F98: R | G98: 61330 | H98: 4 | I98: =IF(OR(Table24[[#This Row],[Rating]]=4,Table24[[#This Row],[Rating]]=5), 0.05*Table24[[#This Row],[Salary]],0) -> 3066.5 | J98: =VLOOKUP(Table24[[#This Row],[Salary]],'Tax rates'!A$2:C$8, 2) + VLOOKUP(Table24[[#This Row],[Salary]],'Tax rates'!A$2:C$8, 3) * (Table24[[#This Row],[Salary]] - VLOOKUP(Table24[[#This Row],[Salary]],'Tax rates'!A$2:C$8,1)) -> 9432.1 | K98: =Table24[[#This Row],[Salary]]-Table24[[#This Row],[Taxes]] -> 51897.9
A99: Herman, Henrietta | B99: Main | C99: Manufacturing | D99: Full Time | E99: 40953 | F99: D | G99: 60380 | H99: 4 | I99: =IF(OR(Table24[[#This Row],[Rating]]=4,Table24[[#This Row],[Rating]]=5), 0.05*Table24[[#This Row],[Salary]],0) -> 3019 | J99: =VLOOKUP(Table24[[#This Row],[Salary]],'Tax rates'!A$2:C$8, 2) + VLOOKUP(Table24[[#This Row],[Salary]],'Tax rates'!A$2:C$8, 3) * (Table24[[#This Row],[Salary]] - VLOOKUP(Table24[[#This Row],[Salary]],'Tax rates'!A$2:C$8,1)) -> 9223.1 | K99: =Table24[[#This Row],[Salary]]-Table24[[#This Row],[Taxes]] -> 51156.9
A100: Osborne, Bill | B100: Main | C100: Manufacturing | D100: Full Time | E100: 38876 | F100: DMR | G100: 60280 | H100: 1 | I100: =IF(OR(Table24[[#This Row],[Rating]]=4,Table24[[#This Row],[Rating]]=5), 0.05*Table24[[#This Row],[Salary]],0) -> 0 | J100: =VLOOKUP(Table24[[#This Row],[Salary]],'Tax rates'!A$2:C$8, 2) + VLOOKUP(Table24[[#This Row],[Salary]],'Tax rates'!A$2:C$8, 3) * (Table24[[#This Row],[Salary]] - VLOOKUP(Table24[[#This Row],[Salary]],'Tax rates'!A$2:C$8,1)) -> 9201.1 | K100: =Table24[[#This Row],[Salary]]-Table24[[#This Row],[Taxes]] -> 51078.9
...

Sheet Data validation lists
A1: Buildings | C1: Departments | E1: Job status | G1: Ratings
A2: Main | C2: Account Management | E2: Contract | G2: 1
A3: North | C3: ADC | E3: Full Time | G3: 2
A4: South | C4: Creative | E4: Half-Time | G4: 3
A5: Taft | C5: Environmental Compliance | E5: Hourly | G5: 4
A6: Watson | C6: Environmental Health/Safety | G6: 5
A7: West | C7: Facilities/Engineering
C8: Green Building
C9: Human Resources
C10: IT
C11: Major Mfg Projects
C12: Manufacturing
C13: Manufacturing Admin
C14: Marketing
C15: Product Development
C16: Professional Training Group
C17: Quality Assurance
C18: Quality Control
C19: Research Center
... C22: Training
